{
  "contributionName": "Pedersen08",
  "objectives": 2,
  "objectiveType": ["int", "int"],
  "direction": ["min", "min"],
  "comments": "Results from the paper by Pedersen et. al (2008)",
  "optimal": true,
  "cpu": {
    "sec": 0,
    "machineSpec": "Intel Xeon 2.67 GHz, 6 GB RAM, Red Hat Enterprise Linux v4.0 OS"
  },
  "valid": true,
  "version": "1.0",
  "instanceName": "Pedersen08_MMAP_d4_e2-8_c0-500_m1_s60_62",
  "suppCard": 12,
  "extCard": 12,
  "card": 55,
  "points": [
    {
      "z1": 61,
      "z2": 1705,
      "type": "se"
    },
    {
      "z1": 63,
      "z2": 1601,
      "type": "se"
    },
    {
      "z1": 103,
      "z2": 1476,
      "type": "se"
    },
    {
      "z1": 127,
      "z2": 1451,
      "type": "us"
    },
    {
      "z1": 152,
      "z2": 1419,
      "type": "us"
    },
    {
      "z1": 158,
      "z2": 1386,
      "type": "us"
    },
    {
      "z1": 167,
      "z2": 1326,
      "type": "se"
    },
    {
      "z1": 199,
      "z2": 1283,
      "type": "us"
    },
    {
      "z1": 220,
      "z2": 1275,
      "type": "us"
    },
    {
      "z1": 224,
      "z2": 1252,
      "type": "us"
    },
    {
      "z1": 244,
      "z2": 1248,
      "type": "us"
    },
    {
      "z1": 248,
      "z2": 1196,
      "type": "us"
    },
    {
      "z1": 272,
      "z2": 1167,
      "type": "us"
    },
    {
      "z1": 274,
      "z2": 1156,
      "type": "us"
    },
    {
      "z1": 284,
      "z2": 1123,
      "type": "us"
    },
    {
      "z1": 305,
      "z2": 1109,
      "type": "us"
    },
    {
      "z1": 321,
      "z2": 1047,
      "type": "us"
    },
    {
      "z1": 348,
      "z2": 1032,
      "type": "us"
    },
    {
      "z1": 357,
      "z2": 1007,
      "type": "us"
    },
    {
      "z1": 370,
      "z2": 960,
      "type": "us"
    },
    {
      "z1": 388,
      "z2": 907,
      "type": "se"
    },
    {
      "z1": 406,
      "z2": 887,
      "type": "us"
    },
    {
      "z1": 441,
      "z2": 856,
      "type": "us"
    },
    {
      "z1": 449,
      "z2": 847,
      "type": "us"
    },
    {
      "z1": 482,
      "z2": 826,
      "type": "us"
    },
    {
      "z1": 485,
      "z2": 805,
      "type": "us"
    },
    {
      "z1": 496,
      "z2": 765,
      "type": "us"
    },
    {
      "z1": 498,
      "z2": 727,
      "type": "se"
    },
    {
      "z1": 591,
      "z2": 695,
      "type": "us"
    },
    {
      "z1": 593,
      "z2": 657,
      "type": "us"
    },
    {
      "z1": 653,
      "z2": 644,
      "type": "us"
    },
    {
      "z1": 661,
      "z2": 626,
      "type": "us"
    },
    {
      "z1": 662,
      "z2": 559,
      "type": "se"
    },
    {
      "z1": 757,
      "z2": 489,
      "type": "us"
    },
    {
      "z1": 777,
      "z2": 477,
      "type": "us"
    },
    {
      "z1": 839,
      "z2": 412,
      "type": "us"
    },
    {
      "z1": 872,
      "z2": 407,
      "type": "us"
    },
    {
      "z1": 898,
      "z2": 388,
      "type": "us"
    },
    {
      "z1": 920,
      "z2": 356,
      "type": "us"
    },
    {
      "z1": 947,
      "z2": 345,
      "type": "us"
    },
    {
      "z1": 954,
      "z2": 330,
      "type": "us"
    },
    {
      "z1": 973,
      "z2": 302,
      "type": "us"
    },
    {
      "z1": 999,
      "z2": 293,
      "type": "us"
    },
    {
      "z1": 1044,
      "z2": 281,
      "type": "us"
    },
    {
      "z1": 1050,
      "z2": 277,
      "type": "us"
    },
    {
      "z1": 1052,
      "z2": 239,
      "type": "us"
    },
    {
      "z1": 1062,
      "z2": 220,
      "type": "se"
    },
    {
      "z1": 1126,
      "z2": 204,
      "type": "us"
    },
    {
      "z1": 1141,
      "z2": 157,
      "type": "se"
    },
    {
      "z1": 1170,
      "z2": 153,
      "type": "us"
    },
    {
      "z1": 1177,
      "z2": 138,
      "type": "us"
    },
    {
      "z1": 1249,
      "z2": 90,
      "type": "us"
    },
    {
      "z1": 1256,
      "z2": 75,
      "type": "se"
    },
    {
      "z1": 1330,
      "z2": 67,
      "type": "se"
    },
    {
      "z1": 1452,
      "z2": 63,
      "type": "se"
    }
  ]
}
