{
  "contributionName": "Pedersen08",
  "objectives": 2,
  "objectiveType": ["int", "int"],
  "direction": ["min", "min"],
  "comments": "Results from the paper by Pedersen et. al (2008)",
  "optimal": true,
  "cpu": {
    "sec": 0.55,
    "machineSpec": "Intel Xeon 2.67 GHz, 6 GB RAM, Red Hat Enterprise Linux v4.0 OS"
  },
  "valid": true,
  "version": "1.0",
  "instanceName": "Pedersen08_MMAP_d8_e10-30_c0-10000_m2_s3_30",
  "suppCard": 27,
  "extCard": 27,
  "card": 1142,
  "points": [
    {
      "z1": 268,
      "z2": 78937,
      "type": "se"
    },
    {
      "z1": 300,
      "z2": 78894,
      "type": "us"
    },
    {
      "z1": 329,
      "z2": 78876,
      "type": "us"
    },
    {
      "z1": 332,
      "z2": 78853,
      "type": "us"
    },
    {
      "z1": 338,
      "z2": 78766,
      "type": "us"
    },
    {
      "z1": 348,
      "z2": 78758,
      "type": "us"
    },
    {
      "z1": 380,
      "z2": 78715,
      "type": "us"
    },
    {
      "z1": 390,
      "z2": 78674,
      "type": "us"
    },
    {
      "z1": 418,
      "z2": 78587,
      "type": "us"
    },
    {
      "z1": 439,
      "z2": 78474,
      "type": "se"
    },
    {
      "z1": 471,
      "z2": 78431,
      "type": "us"
    },
    {
      "z1": 500,
      "z2": 78413,
      "type": "us"
    },
    {
      "z1": 503,
      "z2": 78390,
      "type": "us"
    },
    {
      "z1": 509,
      "z2": 78303,
      "type": "se"
    },
    {
      "z1": 519,
      "z2": 78295,
      "type": "us"
    },
    {
      "z1": 551,
      "z2": 78252,
      "type": "us"
    },
    {
      "z1": 561,
      "z2": 78211,
      "type": "us"
    },
    {
      "z1": 589,
      "z2": 78124,
      "type": "us"
    },
    {
      "z1": 631,
      "z2": 78040,
      "type": "us"
    },
    {
      "z1": 683,
      "z2": 77971,
      "type": "us"
    },
    {
      "z1": 770,
      "z2": 77840,
      "type": "us"
    },
    {
      "z1": 801,
      "z2": 77698,
      "type": "us"
    },
    {
      "z1": 833,
      "z2": 77655,
      "type": "us"
    },
    {
      "z1": 851,
      "z2": 77576,
      "type": "us"
    },
    {
      "z1": 871,
      "z2": 77527,
      "type": "us"
    },
    {
      "z1": 881,
      "z2": 77519,
      "type": "us"
    },
    {
      "z1": 912,
      "z2": 77515,
      "type": "us"
    },
    {
      "z1": 913,
      "z2": 77476,
      "type": "us"
    },
    {
      "z1": 921,
      "z2": 77405,
      "type": "us"
    },
    {
      "z1": 931,
      "z2": 77397,
      "type": "us"
    },
    {
      "z1": 941,
      "z2": 77377,
      "type": "us"
    },
    {
      "z1": 951,
      "z2": 77348,
      "type": "us"
    },
    {
      "z1": 965,
      "z2": 77242,
      "type": "us"
    },
    {
      "z1": 972,
      "z2": 77235,
      "type": "us"
    },
    {
      "z1": 1001,
      "z2": 77226,
      "type": "us"
    },
    {
      "z1": 1004,
      "z2": 77192,
      "type": "us"
    },
    {
      "z1": 1022,
      "z2": 77113,
      "type": "us"
    },
    {
      "z1": 1042,
      "z2": 77064,
      "type": "us"
    },
    {
      "z1": 1045,
      "z2": 77063,
      "type": "us"
    },
    {
      "z1": 1052,
      "z2": 77056,
      "type": "us"
    },
    {
      "z1": 1083,
      "z2": 77052,
      "type": "us"
    },
    {
      "z1": 1084,
      "z2": 77013,
      "type": "us"
    },
    {
      "z1": 1087,
      "z2": 76979,
      "type": "us"
    },
    {
      "z1": 1092,
      "z2": 76942,
      "type": "se"
    },
    {
      "z1": 1102,
      "z2": 76934,
      "type": "us"
    },
    {
      "z1": 1113,
      "z2": 76930,
      "type": "us"
    },
    {
      "z1": 1122,
      "z2": 76885,
      "type": "us"
    },
    {
      "z1": 1144,
      "z2": 76850,
      "type": "us"
    },
    {
      "z1": 1164,
      "z2": 76801,
      "type": "us"
    },
    {
      "z1": 1172,
      "z2": 76763,
      "type": "se"
    },
    {
      "z1": 1183,
      "z2": 76759,
      "type": "us"
    },
    {
      "z1": 1193,
      "z2": 76751,
      "type": "us"
    },
    {
      "z1": 1214,
      "z2": 76679,
      "type": "us"
    },
    {
      "z1": 1235,
      "z2": 76667,
      "type": "us"
    },
    {
      "z1": 1243,
      "z2": 76638,
      "type": "us"
    },
    {
      "z1": 1253,
      "z2": 76630,
      "type": "us"
    },
    {
      "z1": 1263,
      "z2": 76580,
      "type": "us"
    },
    {
      "z1": 1295,
      "z2": 76546,
      "type": "us"
    },
    {
      "z1": 1305,
      "z2": 76496,
      "type": "us"
    },
    {
      "z1": 1323,
      "z2": 76459,
      "type": "se"
    },
    {
      "z1": 1357,
      "z2": 76427,
      "type": "us"
    },
    {
      "z1": 1365,
      "z2": 76375,
      "type": "se"
    },
    {
      "z1": 1417,
      "z2": 76306,
      "type": "us"
    },
    {
      "z1": 1483,
      "z2": 76296,
      "type": "us"
    },
    {
      "z1": 1484,
      "z2": 76295,
      "type": "us"
    },
    {
      "z1": 1492,
      "z2": 76289,
      "type": "us"
    },
    {
      "z1": 1493,
      "z2": 76271,
      "type": "us"
    },
    {
      "z1": 1497,
      "z2": 76251,
      "type": "us"
    },
    {
      "z1": 1503,
      "z2": 76230,
      "type": "us"
    },
    {
      "z1": 1511,
      "z2": 76201,
      "type": "us"
    },
    {
      "z1": 1521,
      "z2": 76193,
      "type": "us"
    },
    {
      "z1": 1531,
      "z2": 76143,
      "type": "us"
    },
    {
      "z1": 1563,
      "z2": 76109,
      "type": "us"
    },
    {
      "z1": 1573,
      "z2": 76059,
      "type": "us"
    },
    {
      "z1": 1591,
      "z2": 76022,
      "type": "us"
    },
    {
      "z1": 1625,
      "z2": 75990,
      "type": "us"
    },
    {
      "z1": 1633,
      "z2": 75938,
      "type": "us"
    },
    {
      "z1": 1656,
      "z2": 75909,
      "type": "us"
    },
    {
      "z1": 1675,
      "z2": 75859,
      "type": "us"
    },
    {
      "z1": 1676,
      "z2": 75774,
      "type": "us"
    },
    {
      "z1": 1737,
      "z2": 75713,
      "type": "us"
    },
    {
      "z1": 1756,
      "z2": 75595,
      "type": "us"
    },
    {
      "z1": 1798,
      "z2": 75511,
      "type": "se"
    },
    {
      "z1": 1850,
      "z2": 75442,
      "type": "us"
    },
    {
      "z1": 1934,
      "z2": 75405,
      "type": "us"
    },
    {
      "z1": 1975,
      "z2": 75402,
      "type": "us"
    },
    {
      "z1": 1976,
      "z2": 75321,
      "type": "us"
    },
    {
      "z1": 1994,
      "z2": 75284,
      "type": "us"
    },
    {
      "z1": 2028,
      "z2": 75252,
      "type": "us"
    },
    {
      "z1": 2036,
      "z2": 75200,
      "type": "us"
    },
    {
      "z1": 2076,
      "z2": 75121,
      "type": "us"
    },
    {
      "z1": 2118,
      "z2": 75037,
      "type": "us"
    },
    {
      "z1": 2170,
      "z2": 74968,
      "type": "us"
    },
    {
      "z1": 2283,
      "z2": 74921,
      "type": "us"
    },
    {
      "z1": 2296,
      "z2": 74899,
      "type": "us"
    },
    {
      "z1": 2302,
      "z2": 74843,
      "type": "us"
    },
    {
      "z1": 2350,
      "z2": 74795,
      "type": "us"
    },
    {
      "z1": 2351,
      "z2": 74736,
      "type": "us"
    },
    {
      "z1": 2378,
      "z2": 74734,
      "type": "us"
    },
    {
      "z1": 2410,
      "z2": 74674,
      "type": "us"
    },
    {
      "z1": 2428,
      "z2": 74628,
      "type": "us"
    },
    {
      "z1": 2457,
      "z2": 74497,
      "type": "us"
    },
    {
      "z1": 2492,
      "z2": 74431,
      "type": "us"
    },
    {
      "z1": 2552,
      "z2": 74310,
      "type": "se"
    },
    {
      "z1": 2682,
      "z2": 74194,
      "type": "us"
    },
    {
      "z1": 2748,
      "z2": 74154,
      "type": "us"
    },
    {
      "z1": 2777,
      "z2": 74023,
      "type": "us"
    },
    {
      "z1": 2857,
      "z2": 74001,
      "type": "us"
    },
    {
      "z1": 2897,
      "z2": 73979,
      "type": "us"
    },
    {
      "z1": 2917,
      "z2": 73953,
      "type": "us"
    },
    {
      "z1": 2952,
      "z2": 73864,
      "type": "us"
    },
    {
      "z1": 3027,
      "z2": 73832,
      "type": "us"
    },
    {
      "z1": 3081,
      "z2": 73794,
      "type": "us"
    },
    {
      "z1": 3104,
      "z2": 73726,
      "type": "us"
    },
    {
      "z1": 3143,
      "z2": 73692,
      "type": "us"
    },
    {
      "z1": 3187,
      "z2": 73632,
      "type": "us"
    },
    {
      "z1": 3217,
      "z2": 73505,
      "type": "us"
    },
    {
      "z1": 3324,
      "z2": 73459,
      "type": "us"
    },
    {
      "z1": 3357,
      "z2": 73435,
      "type": "us"
    },
    {
      "z1": 3380,
      "z2": 73420,
      "type": "us"
    },
    {
      "z1": 3389,
      "z2": 73399,
      "type": "us"
    },
    {
      "z1": 3416,
      "z2": 73382,
      "type": "us"
    },
    {
      "z1": 3419,
      "z2": 73354,
      "type": "us"
    },
    {
      "z1": 3433,
      "z2": 73313,
      "type": "us"
    },
    {
      "z1": 3460,
      "z2": 73311,
      "type": "us"
    },
    {
      "z1": 3478,
      "z2": 73289,
      "type": "us"
    },
    {
      "z1": 3479,
      "z2": 73233,
      "type": "us"
    },
    {
      "z1": 3507,
      "z2": 73158,
      "type": "us"
    },
    {
      "z1": 3545,
      "z2": 73139,
      "type": "us"
    },
    {
      "z1": 3574,
      "z2": 73008,
      "type": "us"
    },
    {
      "z1": 3634,
      "z2": 72887,
      "type": "se"
    },
    {
      "z1": 3714,
      "z2": 72865,
      "type": "us"
    },
    {
      "z1": 3809,
      "z2": 72851,
      "type": "us"
    },
    {
      "z1": 3856,
      "z2": 72832,
      "type": "us"
    },
    {
      "z1": 3873,
      "z2": 72795,
      "type": "us"
    },
    {
      "z1": 3878,
      "z2": 72779,
      "type": "us"
    },
    {
      "z1": 3885,
      "z2": 72701,
      "type": "us"
    },
    {
      "z1": 3938,
      "z2": 72658,
      "type": "us"
    },
    {
      "z1": 3947,
      "z2": 72640,
      "type": "us"
    },
    {
      "z1": 3961,
      "z2": 72590,
      "type": "us"
    },
    {
      "z1": 4014,
      "z2": 72490,
      "type": "us"
    },
    {
      "z1": 4074,
      "z2": 72369,
      "type": "us"
    },
    {
      "z1": 4233,
      "z2": 72368,
      "type": "us"
    },
    {
      "z1": 4242,
      "z2": 72330,
      "type": "us"
    },
    {
      "z1": 4296,
      "z2": 72314,
      "type": "us"
    },
    {
      "z1": 4300,
      "z2": 72275,
      "type": "us"
    },
    {
      "z1": 4302,
      "z2": 72209,
      "type": "us"
    },
    {
      "z1": 4325,
      "z2": 72183,
      "type": "us"
    },
    {
      "z1": 4412,
      "z2": 72101,
      "type": "us"
    },
    {
      "z1": 4441,
      "z2": 71970,
      "type": "us"
    },
    {
      "z1": 4501,
      "z2": 71849,
      "type": "se"
    },
    {
      "z1": 4660,
      "z2": 71848,
      "type": "us"
    },
    {
      "z1": 4666,
      "z2": 71827,
      "type": "us"
    },
    {
      "z1": 4682,
      "z2": 71812,
      "type": "us"
    },
    {
      "z1": 4693,
      "z2": 71793,
      "type": "us"
    },
    {
      "z1": 4697,
      "z2": 71749,
      "type": "us"
    },
    {
      "z1": 4742,
      "z2": 71691,
      "type": "us"
    },
    {
      "z1": 4752,
      "z2": 71663,
      "type": "us"
    },
    {
      "z1": 4757,
      "z2": 71628,
      "type": "us"
    },
    {
      "z1": 4852,
      "z2": 71583,
      "type": "us"
    },
    {
      "z1": 4859,
      "z2": 71539,
      "type": "us"
    },
    {
      "z1": 4881,
      "z2": 71452,
      "type": "us"
    },
    {
      "z1": 4941,
      "z2": 71331,
      "type": "se"
    },
    {
      "z1": 5100,
      "z2": 71330,
      "type": "us"
    },
    {
      "z1": 5106,
      "z2": 71309,
      "type": "us"
    },
    {
      "z1": 5133,
      "z2": 71275,
      "type": "us"
    },
    {
      "z1": 5192,
      "z2": 71145,
      "type": "us"
    },
    {
      "z1": 5299,
      "z2": 71021,
      "type": "us"
    },
    {
      "z1": 5380,
      "z2": 71000,
      "type": "us"
    },
    {
      "z1": 5490,
      "z2": 70957,
      "type": "us"
    },
    {
      "z1": 5491,
      "z2": 70950,
      "type": "us"
    },
    {
      "z1": 5527,
      "z2": 70861,
      "type": "us"
    },
    {
      "z1": 5551,
      "z2": 70829,
      "type": "us"
    },
    {
      "z1": 5646,
      "z2": 70815,
      "type": "us"
    },
    {
      "z1": 5659,
      "z2": 70808,
      "type": "us"
    },
    {
      "z1": 5660,
      "z2": 70757,
      "type": "us"
    },
    {
      "z1": 5683,
      "z2": 70736,
      "type": "us"
    },
    {
      "z1": 5707,
      "z2": 70732,
      "type": "us"
    },
    {
      "z1": 5726,
      "z2": 70501,
      "type": "us"
    },
    {
      "z1": 5873,
      "z2": 70487,
      "type": "us"
    },
    {
      "z1": 5906,
      "z2": 70372,
      "type": "us"
    },
    {
      "z1": 5955,
      "z2": 70314,
      "type": "us"
    },
    {
      "z1": 6082,
      "z2": 70173,
      "type": "us"
    },
    {
      "z1": 6163,
      "z2": 70152,
      "type": "us"
    },
    {
      "z1": 6166,
      "z2": 69983,
      "type": "se"
    },
    {
      "z1": 6454,
      "z2": 69958,
      "type": "us"
    },
    {
      "z1": 6461,
      "z2": 69948,
      "type": "us"
    },
    {
      "z1": 6497,
      "z2": 69850,
      "type": "us"
    },
    {
      "z1": 6526,
      "z2": 69770,
      "type": "us"
    },
    {
      "z1": 6656,
      "z2": 69743,
      "type": "us"
    },
    {
      "z1": 6696,
      "z2": 69490,
      "type": "us"
    },
    {
      "z1": 6930,
      "z2": 69488,
      "type": "us"
    },
    {
      "z1": 6949,
      "z2": 69135,
      "type": "us"
    },
    {
      "z1": 7245,
      "z2": 69116,
      "type": "us"
    },
    {
      "z1": 7295,
      "z2": 69105,
      "type": "us"
    },
    {
      "z1": 7317,
      "z2": 69070,
      "type": "us"
    },
    {
      "z1": 7355,
      "z2": 68984,
      "type": "us"
    },
    {
      "z1": 7370,
      "z2": 68970,
      "type": "us"
    },
    {
      "z1": 7430,
      "z2": 68849,
      "type": "us"
    },
    {
      "z1": 7498,
      "z2": 68761,
      "type": "us"
    },
    {
      "z1": 7602,
      "z2": 68709,
      "type": "us"
    },
    {
      "z1": 7628,
      "z2": 68671,
      "type": "us"
    },
    {
      "z1": 7634,
      "z2": 68661,
      "type": "us"
    },
    {
      "z1": 7726,
      "z2": 68638,
      "type": "us"
    },
    {
      "z1": 7745,
      "z2": 68628,
      "type": "us"
    },
    {
      "z1": 7763,
      "z2": 68585,
      "type": "us"
    },
    {
      "z1": 7768,
      "z2": 68581,
      "type": "us"
    },
    {
      "z1": 7782,
      "z2": 68575,
      "type": "us"
    },
    {
      "z1": 7786,
      "z2": 68517,
      "type": "us"
    },
    {
      "z1": 7797,
      "z2": 68450,
      "type": "us"
    },
    {
      "z1": 7857,
      "z2": 68329,
      "type": "us"
    },
    {
      "z1": 7934,
      "z2": 68325,
      "type": "us"
    },
    {
      "z1": 7995,
      "z2": 68272,
      "type": "us"
    },
    {
      "z1": 8001,
      "z2": 68262,
      "type": "us"
    },
    {
      "z1": 8053,
      "z2": 68229,
      "type": "us"
    },
    {
      "z1": 8055,
      "z2": 68151,
      "type": "us"
    },
    {
      "z1": 8061,
      "z2": 68141,
      "type": "us"
    },
    {
      "z1": 8113,
      "z2": 68108,
      "type": "us"
    },
    {
      "z1": 8208,
      "z2": 68063,
      "type": "us"
    },
    {
      "z1": 8215,
      "z2": 68019,
      "type": "us"
    },
    {
      "z1": 8237,
      "z2": 67932,
      "type": "us"
    },
    {
      "z1": 8297,
      "z2": 67811,
      "type": "us"
    },
    {
      "z1": 8374,
      "z2": 67807,
      "type": "us"
    },
    {
      "z1": 8435,
      "z2": 67754,
      "type": "us"
    },
    {
      "z1": 8441,
      "z2": 67744,
      "type": "us"
    },
    {
      "z1": 8495,
      "z2": 67633,
      "type": "us"
    },
    {
      "z1": 8501,
      "z2": 67623,
      "type": "us"
    },
    {
      "z1": 8625,
      "z2": 67621,
      "type": "us"
    },
    {
      "z1": 8655,
      "z2": 67501,
      "type": "us"
    },
    {
      "z1": 8736,
      "z2": 67480,
      "type": "us"
    },
    {
      "z1": 8737,
      "z2": 67478,
      "type": "us"
    },
    {
      "z1": 8746,
      "z2": 67447,
      "type": "us"
    },
    {
      "z1": 8752,
      "z2": 67437,
      "type": "us"
    },
    {
      "z1": 8847,
      "z2": 67430,
      "type": "us"
    },
    {
      "z1": 8864,
      "z2": 67337,
      "type": "us"
    },
    {
      "z1": 8883,
      "z2": 67327,
      "type": "us"
    },
    {
      "z1": 8907,
      "z2": 67309,
      "type": "us"
    },
    {
      "z1": 8964,
      "z2": 67306,
      "type": "us"
    },
    {
      "z1": 8976,
      "z2": 67243,
      "type": "us"
    },
    {
      "z1": 9016,
      "z2": 67237,
      "type": "us"
    },
    {
      "z1": 9039,
      "z2": 67216,
      "type": "us"
    },
    {
      "z1": 9059,
      "z2": 67156,
      "type": "us"
    },
    {
      "z1": 9082,
      "z2": 66981,
      "type": "us"
    },
    {
      "z1": 9229,
      "z2": 66967,
      "type": "us"
    },
    {
      "z1": 9262,
      "z2": 66852,
      "type": "us"
    },
    {
      "z1": 9311,
      "z2": 66794,
      "type": "us"
    },
    {
      "z1": 9438,
      "z2": 66653,
      "type": "us"
    },
    {
      "z1": 9519,
      "z2": 66632,
      "type": "us"
    },
    {
      "z1": 9522,
      "z2": 66463,
      "type": "us"
    },
    {
      "z1": 9731,
      "z2": 66299,
      "type": "us"
    },
    {
      "z1": 9750,
      "z2": 66289,
      "type": "us"
    },
    {
      "z1": 9882,
      "z2": 66250,
      "type": "us"
    },
    {
      "z1": 10012,
      "z2": 66223,
      "type": "us"
    },
    {
      "z1": 10052,
      "z2": 65970,
      "type": "us"
    },
    {
      "z1": 10280,
      "z2": 65925,
      "type": "us"
    },
    {
      "z1": 10299,
      "z2": 65915,
      "type": "us"
    },
    {
      "z1": 10305,
      "z2": 65615,
      "type": "us"
    },
    {
      "z1": 10601,
      "z2": 65596,
      "type": "us"
    },
    {
      "z1": 10694,
      "z2": 65509,
      "type": "us"
    },
    {
      "z1": 10740,
      "z2": 65486,
      "type": "us"
    },
    {
      "z1": 10795,
      "z2": 65483,
      "type": "us"
    },
    {
      "z1": 10797,
      "z2": 65479,
      "type": "us"
    },
    {
      "z1": 10801,
      "z2": 65473,
      "type": "us"
    },
    {
      "z1": 10803,
      "z2": 65446,
      "type": "us"
    },
    {
      "z1": 10805,
      "z2": 65373,
      "type": "us"
    },
    {
      "z1": 10854,
      "z2": 65241,
      "type": "us"
    },
    {
      "z1": 10924,
      "z2": 65208,
      "type": "us"
    },
    {
      "z1": 10984,
      "z2": 65151,
      "type": "us"
    },
    {
      "z1": 10990,
      "z2": 65141,
      "type": "us"
    },
    {
      "z1": 11086,
      "z2": 65130,
      "type": "us"
    },
    {
      "z1": 11098,
      "z2": 65120,
      "type": "us"
    },
    {
      "z1": 11104,
      "z2": 65110,
      "type": "us"
    },
    {
      "z1": 11117,
      "z2": 65074,
      "type": "us"
    },
    {
      "z1": 11121,
      "z2": 65068,
      "type": "us"
    },
    {
      "z1": 11150,
      "z2": 64937,
      "type": "us"
    },
    {
      "z1": 11230,
      "z2": 64926,
      "type": "us"
    },
    {
      "z1": 11256,
      "z2": 64835,
      "type": "us"
    },
    {
      "z1": 11290,
      "z2": 64805,
      "type": "us"
    },
    {
      "z1": 11316,
      "z2": 64714,
      "type": "us"
    },
    {
      "z1": 11411,
      "z2": 64631,
      "type": "us"
    },
    {
      "z1": 11417,
      "z2": 64621,
      "type": "us"
    },
    {
      "z1": 11441,
      "z2": 64594,
      "type": "us"
    },
    {
      "z1": 11470,
      "z2": 64463,
      "type": "us"
    },
    {
      "z1": 11629,
      "z2": 64462,
      "type": "us"
    },
    {
      "z1": 11643,
      "z2": 64439,
      "type": "us"
    },
    {
      "z1": 11668,
      "z2": 64435,
      "type": "us"
    },
    {
      "z1": 11670,
      "z2": 64408,
      "type": "us"
    },
    {
      "z1": 11674,
      "z2": 64404,
      "type": "us"
    },
    {
      "z1": 11723,
      "z2": 64370,
      "type": "us"
    },
    {
      "z1": 11730,
      "z2": 64287,
      "type": "us"
    },
    {
      "z1": 11783,
      "z2": 64249,
      "type": "us"
    },
    {
      "z1": 11791,
      "z2": 64170,
      "type": "us"
    },
    {
      "z1": 11848,
      "z2": 64136,
      "type": "us"
    },
    {
      "z1": 11851,
      "z2": 64113,
      "type": "us"
    },
    {
      "z1": 11857,
      "z2": 64103,
      "type": "us"
    },
    {
      "z1": 11981,
      "z2": 64064,
      "type": "us"
    },
    {
      "z1": 12029,
      "z2": 64061,
      "type": "us"
    },
    {
      "z1": 12039,
      "z2": 64057,
      "type": "us"
    },
    {
      "z1": 12041,
      "z2": 63943,
      "type": "us"
    },
    {
      "z1": 12082,
      "z2": 63839,
      "type": "us"
    },
    {
      "z1": 12126,
      "z2": 63753,
      "type": "us"
    },
    {
      "z1": 12153,
      "z2": 63751,
      "type": "us"
    },
    {
      "z1": 12214,
      "z2": 63684,
      "type": "us"
    },
    {
      "z1": 12238,
      "z2": 63579,
      "type": "us"
    },
    {
      "z1": 12267,
      "z2": 63448,
      "type": "us"
    },
    {
      "z1": 12327,
      "z2": 63327,
      "type": "us"
    },
    {
      "z1": 12486,
      "z2": 63326,
      "type": "us"
    },
    {
      "z1": 12549,
      "z2": 63272,
      "type": "us"
    },
    {
      "z1": 12578,
      "z2": 63141,
      "type": "us"
    },
    {
      "z1": 12702,
      "z2": 63101,
      "type": "us"
    },
    {
      "z1": 12816,
      "z2": 63074,
      "type": "us"
    },
    {
      "z1": 12853,
      "z2": 63030,
      "type": "us"
    },
    {
      "z1": 12865,
      "z2": 63029,
      "type": "us"
    },
    {
      "z1": 12869,
      "z2": 62982,
      "type": "us"
    },
    {
      "z1": 12876,
      "z2": 62953,
      "type": "us"
    },
    {
      "z1": 12919,
      "z2": 62898,
      "type": "us"
    },
    {
      "z1": 12929,
      "z2": 62861,
      "type": "us"
    },
    {
      "z1": 13016,
      "z2": 62822,
      "type": "us"
    },
    {
      "z1": 13032,
      "z2": 62780,
      "type": "us"
    },
    {
      "z1": 13061,
      "z2": 62649,
      "type": "us"
    },
    {
      "z1": 13121,
      "z2": 62528,
      "type": "us"
    },
    {
      "z1": 13259,
      "z2": 62483,
      "type": "us"
    },
    {
      "z1": 13328,
      "z2": 62455,
      "type": "us"
    },
    {
      "z1": 13372,
      "z2": 62342,
      "type": "us"
    },
    {
      "z1": 13457,
      "z2": 62257,
      "type": "us"
    },
    {
      "z1": 13486,
      "z2": 62126,
      "type": "us"
    },
    {
      "z1": 13552,
      "z2": 61979,
      "type": "us"
    },
    {
      "z1": 13847,
      "z2": 61944,
      "type": "us"
    },
    {
      "z1": 13871,
      "z2": 61900,
      "type": "us"
    },
    {
      "z1": 13900,
      "z2": 61769,
      "type": "us"
    },
    {
      "z1": 13912,
      "z2": 61766,
      "type": "us"
    },
    {
      "z1": 14035,
      "z2": 61752,
      "type": "us"
    },
    {
      "z1": 14053,
      "z2": 61684,
      "type": "us"
    },
    {
      "z1": 14068,
      "z2": 61655,
      "type": "us"
    },
    {
      "z1": 14082,
      "z2": 61486,
      "type": "us"
    },
    {
      "z1": 14269,
      "z2": 61471,
      "type": "us"
    },
    {
      "z1": 14341,
      "z2": 61412,
      "type": "us"
    },
    {
      "z1": 14346,
      "z2": 61180,
      "type": "us"
    },
    {
      "z1": 14623,
      "z2": 61148,
      "type": "us"
    },
    {
      "z1": 14631,
      "z2": 61112,
      "type": "us"
    },
    {
      "z1": 14648,
      "z2": 61081,
      "type": "us"
    },
    {
      "z1": 14684,
      "z2": 61020,
      "type": "us"
    },
    {
      "z1": 14706,
      "z2": 60967,
      "type": "us"
    },
    {
      "z1": 14748,
      "z2": 60954,
      "type": "us"
    },
    {
      "z1": 14826,
      "z2": 60943,
      "type": "us"
    },
    {
      "z1": 14868,
      "z2": 60910,
      "type": "us"
    },
    {
      "z1": 14876,
      "z2": 60687,
      "type": "us"
    },
    {
      "z1": 15036,
      "z2": 60560,
      "type": "us"
    },
    {
      "z1": 15163,
      "z2": 60508,
      "type": "us"
    },
    {
      "z1": 15188,
      "z2": 60436,
      "type": "us"
    },
    {
      "z1": 15295,
      "z2": 60390,
      "type": "us"
    },
    {
      "z1": 15328,
      "z2": 60366,
      "type": "us"
    },
    {
      "z1": 15351,
      "z2": 60351,
      "type": "us"
    },
    {
      "z1": 15360,
      "z2": 60330,
      "type": "us"
    },
    {
      "z1": 15387,
      "z2": 60313,
      "type": "us"
    },
    {
      "z1": 15404,
      "z2": 60244,
      "type": "us"
    },
    {
      "z1": 15431,
      "z2": 60242,
      "type": "us"
    },
    {
      "z1": 15478,
      "z2": 60089,
      "type": "us"
    },
    {
      "z1": 15545,
      "z2": 59939,
      "type": "us"
    },
    {
      "z1": 15605,
      "z2": 59818,
      "type": "us"
    },
    {
      "z1": 15683,
      "z2": 59807,
      "type": "us"
    },
    {
      "z1": 15760,
      "z2": 59803,
      "type": "us"
    },
    {
      "z1": 15821,
      "z2": 59750,
      "type": "us"
    },
    {
      "z1": 15827,
      "z2": 59740,
      "type": "us"
    },
    {
      "z1": 15844,
      "z2": 59726,
      "type": "us"
    },
    {
      "z1": 15856,
      "z2": 59632,
      "type": "us"
    },
    {
      "z1": 15881,
      "z2": 59629,
      "type": "us"
    },
    {
      "z1": 15887,
      "z2": 59619,
      "type": "us"
    },
    {
      "z1": 15918,
      "z2": 59571,
      "type": "us"
    },
    {
      "z1": 15985,
      "z2": 59421,
      "type": "us"
    },
    {
      "z1": 16045,
      "z2": 59300,
      "type": "us"
    },
    {
      "z1": 16213,
      "z2": 59261,
      "type": "us"
    },
    {
      "z1": 16271,
      "z2": 59206,
      "type": "us"
    },
    {
      "z1": 16273,
      "z2": 59140,
      "type": "us"
    },
    {
      "z1": 16296,
      "z2": 59114,
      "type": "us"
    },
    {
      "z1": 16412,
      "z2": 58901,
      "type": "us"
    },
    {
      "z1": 16472,
      "z2": 58780,
      "type": "us"
    },
    {
      "z1": 16637,
      "z2": 58758,
      "type": "us"
    },
    {
      "z1": 16653,
      "z2": 58743,
      "type": "us"
    },
    {
      "z1": 16711,
      "z2": 58688,
      "type": "us"
    },
    {
      "z1": 16713,
      "z2": 58622,
      "type": "us"
    },
    {
      "z1": 16723,
      "z2": 58594,
      "type": "us"
    },
    {
      "z1": 16852,
      "z2": 58383,
      "type": "us"
    },
    {
      "z1": 16912,
      "z2": 58262,
      "type": "se"
    },
    {
      "z1": 17077,
      "z2": 58240,
      "type": "us"
    },
    {
      "z1": 17163,
      "z2": 58076,
      "type": "us"
    },
    {
      "z1": 17401,
      "z2": 58009,
      "type": "us"
    },
    {
      "z1": 17438,
      "z2": 57966,
      "type": "us"
    },
    {
      "z1": 17461,
      "z2": 57888,
      "type": "us"
    },
    {
      "z1": 17491,
      "z2": 57883,
      "type": "us"
    },
    {
      "z1": 17573,
      "z2": 57870,
      "type": "us"
    },
    {
      "z1": 17626,
      "z2": 57866,
      "type": "us"
    },
    {
      "z1": 17649,
      "z2": 57817,
      "type": "us"
    },
    {
      "z1": 17702,
      "z2": 57660,
      "type": "us"
    },
    {
      "z1": 17916,
      "z2": 57549,
      "type": "us"
    },
    {
      "z1": 17957,
      "z2": 57493,
      "type": "us"
    },
    {
      "z1": 18062,
      "z2": 57447,
      "type": "us"
    },
    {
      "z1": 18198,
      "z2": 57443,
      "type": "us"
    },
    {
      "z1": 18230,
      "z2": 57406,
      "type": "us"
    },
    {
      "z1": 18232,
      "z2": 57167,
      "type": "us"
    },
    {
      "z1": 18371,
      "z2": 57136,
      "type": "us"
    },
    {
      "z1": 18392,
      "z2": 57040,
      "type": "us"
    },
    {
      "z1": 18519,
      "z2": 56988,
      "type": "us"
    },
    {
      "z1": 18603,
      "z2": 56945,
      "type": "us"
    },
    {
      "z1": 18658,
      "z2": 56885,
      "type": "us"
    },
    {
      "z1": 18668,
      "z2": 56798,
      "type": "us"
    },
    {
      "z1": 18728,
      "z2": 56677,
      "type": "us"
    },
    {
      "z1": 18809,
      "z2": 56599,
      "type": "us"
    },
    {
      "z1": 18979,
      "z2": 56491,
      "type": "us"
    },
    {
      "z1": 19040,
      "z2": 56413,
      "type": "us"
    },
    {
      "z1": 19056,
      "z2": 56404,
      "type": "us"
    },
    {
      "z1": 19116,
      "z2": 56283,
      "type": "us"
    },
    {
      "z1": 19177,
      "z2": 56230,
      "type": "us"
    },
    {
      "z1": 19183,
      "z2": 56220,
      "type": "us"
    },
    {
      "z1": 19237,
      "z2": 56109,
      "type": "us"
    },
    {
      "z1": 19243,
      "z2": 56099,
      "type": "us"
    },
    {
      "z1": 19321,
      "z2": 56089,
      "type": "us"
    },
    {
      "z1": 19399,
      "z2": 56078,
      "type": "us"
    },
    {
      "z1": 19441,
      "z2": 56039,
      "type": "us"
    },
    {
      "z1": 19451,
      "z2": 55998,
      "type": "us"
    },
    {
      "z1": 19455,
      "z2": 55870,
      "type": "us"
    },
    {
      "z1": 19515,
      "z2": 55749,
      "type": "us"
    },
    {
      "z1": 19682,
      "z2": 55719,
      "type": "us"
    },
    {
      "z1": 19689,
      "z2": 55705,
      "type": "us"
    },
    {
      "z1": 19725,
      "z2": 55703,
      "type": "us"
    },
    {
      "z1": 19747,
      "z2": 55606,
      "type": "us"
    },
    {
      "z1": 19754,
      "z2": 55592,
      "type": "us"
    },
    {
      "z1": 19761,
      "z2": 55571,
      "type": "us"
    },
    {
      "z1": 19766,
      "z2": 55563,
      "type": "us"
    },
    {
      "z1": 19841,
      "z2": 55518,
      "type": "us"
    },
    {
      "z1": 19887,
      "z2": 55476,
      "type": "us"
    },
    {
      "z1": 19940,
      "z2": 55413,
      "type": "us"
    },
    {
      "z1": 19947,
      "z2": 55399,
      "type": "us"
    },
    {
      "z1": 19968,
      "z2": 55398,
      "type": "us"
    },
    {
      "z1": 19971,
      "z2": 55389,
      "type": "us"
    },
    {
      "z1": 19980,
      "z2": 55377,
      "type": "us"
    },
    {
      "z1": 20028,
      "z2": 55363,
      "type": "us"
    },
    {
      "z1": 20031,
      "z2": 55310,
      "type": "us"
    },
    {
      "z1": 20037,
      "z2": 55300,
      "type": "us"
    },
    {
      "z1": 20117,
      "z2": 55283,
      "type": "us"
    },
    {
      "z1": 20125,
      "z2": 55269,
      "type": "us"
    },
    {
      "z1": 20164,
      "z2": 55196,
      "type": "us"
    },
    {
      "z1": 20188,
      "z2": 55051,
      "type": "us"
    },
    {
      "z1": 20309,
      "z2": 54950,
      "type": "us"
    },
    {
      "z1": 20396,
      "z2": 54908,
      "type": "us"
    },
    {
      "z1": 20402,
      "z2": 54898,
      "type": "us"
    },
    {
      "z1": 20420,
      "z2": 54826,
      "type": "us"
    },
    {
      "z1": 20541,
      "z2": 54807,
      "type": "us"
    },
    {
      "z1": 20547,
      "z2": 54685,
      "type": "us"
    },
    {
      "z1": 20614,
      "z2": 54621,
      "type": "us"
    },
    {
      "z1": 20628,
      "z2": 54533,
      "type": "us"
    },
    {
      "z1": 20679,
      "z2": 54508,
      "type": "us"
    },
    {
      "z1": 20847,
      "z2": 54339,
      "type": "us"
    },
    {
      "z1": 20872,
      "z2": 54315,
      "type": "us"
    },
    {
      "z1": 20915,
      "z2": 54289,
      "type": "us"
    },
    {
      "z1": 20960,
      "z2": 54265,
      "type": "us"
    },
    {
      "z1": 21058,
      "z2": 54108,
      "type": "us"
    },
    {
      "z1": 21118,
      "z2": 53987,
      "type": "us"
    },
    {
      "z1": 21287,
      "z2": 53821,
      "type": "us"
    },
    {
      "z1": 21369,
      "z2": 53801,
      "type": "us"
    },
    {
      "z1": 21414,
      "z2": 53647,
      "type": "us"
    },
    {
      "z1": 21649,
      "z2": 53611,
      "type": "us"
    },
    {
      "z1": 21666,
      "z2": 53516,
      "type": "us"
    },
    {
      "z1": 21709,
      "z2": 53490,
      "type": "us"
    },
    {
      "z1": 21754,
      "z2": 53466,
      "type": "us"
    },
    {
      "z1": 21836,
      "z2": 53447,
      "type": "us"
    },
    {
      "z1": 21852,
      "z2": 53309,
      "type": "us"
    },
    {
      "z1": 21912,
      "z2": 53188,
      "type": "us"
    },
    {
      "z1": 22074,
      "z2": 53088,
      "type": "us"
    },
    {
      "z1": 22163,
      "z2": 53002,
      "type": "us"
    },
    {
      "z1": 22266,
      "z2": 52999,
      "type": "us"
    },
    {
      "z1": 22277,
      "z2": 52786,
      "type": "us"
    },
    {
      "z1": 22399,
      "z2": 52778,
      "type": "us"
    },
    {
      "z1": 22420,
      "z2": 52683,
      "type": "us"
    },
    {
      "z1": 22459,
      "z2": 52657,
      "type": "us"
    },
    {
      "z1": 22650,
      "z2": 52651,
      "type": "us"
    },
    {
      "z1": 22671,
      "z2": 52497,
      "type": "us"
    },
    {
      "z1": 22691,
      "z2": 52429,
      "type": "us"
    },
    {
      "z1": 22768,
      "z2": 52410,
      "type": "us"
    },
    {
      "z1": 22835,
      "z2": 52260,
      "type": "us"
    },
    {
      "z1": 22895,
      "z2": 52139,
      "type": "us"
    },
    {
      "z1": 23028,
      "z2": 52126,
      "type": "us"
    },
    {
      "z1": 23086,
      "z2": 52071,
      "type": "us"
    },
    {
      "z1": 23088,
      "z2": 52005,
      "type": "us"
    },
    {
      "z1": 23103,
      "z2": 51973,
      "type": "us"
    },
    {
      "z1": 23121,
      "z2": 51868,
      "type": "us"
    },
    {
      "z1": 23227,
      "z2": 51766,
      "type": "us"
    },
    {
      "z1": 23287,
      "z2": 51645,
      "type": "us"
    },
    {
      "z1": 23395,
      "z2": 51622,
      "type": "us"
    },
    {
      "z1": 23427,
      "z2": 51563,
      "type": "us"
    },
    {
      "z1": 23441,
      "z2": 51394,
      "type": "us"
    },
    {
      "z1": 23614,
      "z2": 51370,
      "type": "us"
    },
    {
      "z1": 23702,
      "z2": 51222,
      "type": "us"
    },
    {
      "z1": 23762,
      "z2": 51101,
      "type": "us"
    },
    {
      "z1": 23915,
      "z2": 51069,
      "type": "us"
    },
    {
      "z1": 23972,
      "z2": 51034,
      "type": "us"
    },
    {
      "z1": 23990,
      "z2": 51020,
      "type": "us"
    },
    {
      "z1": 24000,
      "z2": 50992,
      "type": "us"
    },
    {
      "z1": 24010,
      "z2": 50988,
      "type": "us"
    },
    {
      "z1": 24013,
      "z2": 50915,
      "type": "us"
    },
    {
      "z1": 24053,
      "z2": 50770,
      "type": "us"
    },
    {
      "z1": 24097,
      "z2": 50684,
      "type": "us"
    },
    {
      "z1": 24124,
      "z2": 50682,
      "type": "us"
    },
    {
      "z1": 24185,
      "z2": 50615,
      "type": "us"
    },
    {
      "z1": 24224,
      "z2": 50548,
      "type": "us"
    },
    {
      "z1": 24238,
      "z2": 50379,
      "type": "us"
    },
    {
      "z1": 24298,
      "z2": 50258,
      "type": "se"
    },
    {
      "z1": 24535,
      "z2": 50241,
      "type": "us"
    },
    {
      "z1": 24549,
      "z2": 50072,
      "type": "us"
    },
    {
      "z1": 24787,
      "z2": 50005,
      "type": "us"
    },
    {
      "z1": 24829,
      "z2": 49982,
      "type": "us"
    },
    {
      "z1": 24840,
      "z2": 49913,
      "type": "us"
    },
    {
      "z1": 24847,
      "z2": 49884,
      "type": "us"
    },
    {
      "z1": 24900,
      "z2": 49792,
      "type": "us"
    },
    {
      "z1": 25019,
      "z2": 49752,
      "type": "us"
    },
    {
      "z1": 25032,
      "z2": 49580,
      "type": "us"
    },
    {
      "z1": 25092,
      "z2": 49459,
      "type": "us"
    },
    {
      "z1": 25299,
      "z2": 49386,
      "type": "us"
    },
    {
      "z1": 25343,
      "z2": 49273,
      "type": "us"
    },
    {
      "z1": 25457,
      "z2": 49057,
      "type": "us"
    },
    {
      "z1": 25829,
      "z2": 49014,
      "type": "us"
    },
    {
      "z1": 25848,
      "z2": 49012,
      "type": "us"
    },
    {
      "z1": 25871,
      "z2": 48700,
      "type": "us"
    },
    {
      "z1": 26006,
      "z2": 48683,
      "type": "us"
    },
    {
      "z1": 26378,
      "z2": 48640,
      "type": "us"
    },
    {
      "z1": 26379,
      "z2": 48505,
      "type": "us"
    },
    {
      "z1": 26420,
      "z2": 48326,
      "type": "us"
    },
    {
      "z1": 26731,
      "z2": 48316,
      "type": "us"
    },
    {
      "z1": 26751,
      "z2": 48300,
      "type": "us"
    },
    {
      "z1": 26757,
      "z2": 48290,
      "type": "us"
    },
    {
      "z1": 26762,
      "z2": 48266,
      "type": "us"
    },
    {
      "z1": 26795,
      "z2": 48242,
      "type": "us"
    },
    {
      "z1": 26834,
      "z2": 48216,
      "type": "us"
    },
    {
      "z1": 26851,
      "z2": 48065,
      "type": "us"
    },
    {
      "z1": 26879,
      "z2": 47985,
      "type": "us"
    },
    {
      "z1": 26944,
      "z2": 47934,
      "type": "us"
    },
    {
      "z1": 27003,
      "z2": 47916,
      "type": "us"
    },
    {
      "z1": 27059,
      "z2": 47827,
      "type": "us"
    },
    {
      "z1": 27082,
      "z2": 47792,
      "type": "us"
    },
    {
      "z1": 27217,
      "z2": 47778,
      "type": "us"
    },
    {
      "z1": 27269,
      "z2": 47760,
      "type": "us"
    },
    {
      "z1": 27270,
      "z2": 47698,
      "type": "us"
    },
    {
      "z1": 27310,
      "z2": 47641,
      "type": "us"
    },
    {
      "z1": 27314,
      "z2": 47560,
      "type": "us"
    },
    {
      "z1": 27407,
      "z2": 47461,
      "type": "us"
    },
    {
      "z1": 27428,
      "z2": 47435,
      "type": "us"
    },
    {
      "z1": 27446,
      "z2": 47327,
      "type": "us"
    },
    {
      "z1": 27645,
      "z2": 47266,
      "type": "us"
    },
    {
      "z1": 27652,
      "z2": 47214,
      "type": "us"
    },
    {
      "z1": 27662,
      "z2": 47204,
      "type": "us"
    },
    {
      "z1": 27673,
      "z2": 47186,
      "type": "us"
    },
    {
      "z1": 27718,
      "z2": 47180,
      "type": "us"
    },
    {
      "z1": 27738,
      "z2": 47135,
      "type": "us"
    },
    {
      "z1": 27826,
      "z2": 47122,
      "type": "us"
    },
    {
      "z1": 27840,
      "z2": 46953,
      "type": "us"
    },
    {
      "z1": 27884,
      "z2": 46877,
      "type": "us"
    },
    {
      "z1": 27970,
      "z2": 46850,
      "type": "us"
    },
    {
      "z1": 27997,
      "z2": 46848,
      "type": "us"
    },
    {
      "z1": 28000,
      "z2": 46698,
      "type": "us"
    },
    {
      "z1": 28014,
      "z2": 46529,
      "type": "us"
    },
    {
      "z1": 28171,
      "z2": 46424,
      "type": "us"
    },
    {
      "z1": 28381,
      "z2": 46373,
      "type": "us"
    },
    {
      "z1": 28422,
      "z2": 46238,
      "type": "us"
    },
    {
      "z1": 28544,
      "z2": 46212,
      "type": "us"
    },
    {
      "z1": 28563,
      "z2": 46155,
      "type": "us"
    },
    {
      "z1": 28616,
      "z2": 46063,
      "type": "us"
    },
    {
      "z1": 28659,
      "z2": 45986,
      "type": "us"
    },
    {
      "z1": 28673,
      "z2": 45817,
      "type": "us"
    },
    {
      "z1": 28808,
      "z2": 45730,
      "type": "us"
    },
    {
      "z1": 29079,
      "z2": 45640,
      "type": "us"
    },
    {
      "z1": 29143,
      "z2": 45540,
      "type": "us"
    },
    {
      "z1": 29222,
      "z2": 45443,
      "type": "us"
    },
    {
      "z1": 29254,
      "z2": 45372,
      "type": "us"
    },
    {
      "z1": 29275,
      "z2": 45351,
      "type": "us"
    },
    {
      "z1": 29467,
      "z2": 45018,
      "type": "us"
    },
    {
      "z1": 29796,
      "z2": 45013,
      "type": "us"
    },
    {
      "z1": 29803,
      "z2": 44998,
      "type": "us"
    },
    {
      "z1": 29824,
      "z2": 44977,
      "type": "us"
    },
    {
      "z1": 29913,
      "z2": 44969,
      "type": "us"
    },
    {
      "z1": 29973,
      "z2": 44848,
      "type": "us"
    },
    {
      "z1": 29991,
      "z2": 44844,
      "type": "us"
    },
    {
      "z1": 30016,
      "z2": 44644,
      "type": "us"
    },
    {
      "z1": 30165,
      "z2": 44615,
      "type": "us"
    },
    {
      "z1": 30222,
      "z2": 44600,
      "type": "us"
    },
    {
      "z1": 30230,
      "z2": 44502,
      "type": "us"
    },
    {
      "z1": 30382,
      "z2": 44473,
      "type": "us"
    },
    {
      "z1": 30422,
      "z2": 44448,
      "type": "us"
    },
    {
      "z1": 30423,
      "z2": 44309,
      "type": "us"
    },
    {
      "z1": 30511,
      "z2": 44259,
      "type": "us"
    },
    {
      "z1": 30599,
      "z2": 44146,
      "type": "us"
    },
    {
      "z1": 30635,
      "z2": 44059,
      "type": "us"
    },
    {
      "z1": 30673,
      "z2": 44035,
      "type": "us"
    },
    {
      "z1": 30733,
      "z2": 43914,
      "type": "us"
    },
    {
      "z1": 30817,
      "z2": 43816,
      "type": "us"
    },
    {
      "z1": 30862,
      "z2": 43796,
      "type": "us"
    },
    {
      "z1": 30877,
      "z2": 43695,
      "type": "us"
    },
    {
      "z1": 30955,
      "z2": 43585,
      "type": "us"
    },
    {
      "z1": 31128,
      "z2": 43509,
      "type": "us"
    },
    {
      "z1": 31293,
      "z2": 43497,
      "type": "us"
    },
    {
      "z1": 31295,
      "z2": 43432,
      "type": "us"
    },
    {
      "z1": 31317,
      "z2": 43413,
      "type": "us"
    },
    {
      "z1": 31354,
      "z2": 43350,
      "type": "us"
    },
    {
      "z1": 31393,
      "z2": 43347,
      "type": "us"
    },
    {
      "z1": 31426,
      "z2": 43321,
      "type": "us"
    },
    {
      "z1": 31437,
      "z2": 43299,
      "type": "us"
    },
    {
      "z1": 31467,
      "z2": 43236,
      "type": "us"
    },
    {
      "z1": 31478,
      "z2": 43226,
      "type": "us"
    },
    {
      "z1": 31481,
      "z2": 43176,
      "type": "us"
    },
    {
      "z1": 31527,
      "z2": 43115,
      "type": "us"
    },
    {
      "z1": 31541,
      "z2": 43055,
      "type": "us"
    },
    {
      "z1": 31567,
      "z2": 42961,
      "type": "us"
    },
    {
      "z1": 31611,
      "z2": 42875,
      "type": "us"
    },
    {
      "z1": 31638,
      "z2": 42873,
      "type": "us"
    },
    {
      "z1": 31699,
      "z2": 42806,
      "type": "us"
    },
    {
      "z1": 31752,
      "z2": 42570,
      "type": "us"
    },
    {
      "z1": 31812,
      "z2": 42449,
      "type": "se"
    },
    {
      "z1": 32063,
      "z2": 42263,
      "type": "us"
    },
    {
      "z1": 32301,
      "z2": 42196,
      "type": "us"
    },
    {
      "z1": 32361,
      "z2": 42075,
      "type": "us"
    },
    {
      "z1": 32501,
      "z2": 42045,
      "type": "us"
    },
    {
      "z1": 32546,
      "z2": 41983,
      "type": "us"
    },
    {
      "z1": 32612,
      "z2": 41889,
      "type": "us"
    },
    {
      "z1": 32714,
      "z2": 41850,
      "type": "us"
    },
    {
      "z1": 32771,
      "z2": 41847,
      "type": "us"
    },
    {
      "z1": 32790,
      "z2": 41834,
      "type": "us"
    },
    {
      "z1": 32814,
      "z2": 41810,
      "type": "us"
    },
    {
      "z1": 32820,
      "z2": 41601,
      "type": "us"
    },
    {
      "z1": 32840,
      "z2": 41583,
      "type": "us"
    },
    {
      "z1": 33050,
      "z2": 41573,
      "type": "us"
    },
    {
      "z1": 33128,
      "z2": 41524,
      "type": "us"
    },
    {
      "z1": 33132,
      "z2": 41482,
      "type": "us"
    },
    {
      "z1": 33136,
      "z2": 41445,
      "type": "us"
    },
    {
      "z1": 33244,
      "z2": 41333,
      "type": "us"
    },
    {
      "z1": 33252,
      "z2": 41210,
      "type": "us"
    },
    {
      "z1": 33306,
      "z2": 41058,
      "type": "us"
    },
    {
      "z1": 33418,
      "z2": 40909,
      "type": "us"
    },
    {
      "z1": 33829,
      "z2": 40814,
      "type": "us"
    },
    {
      "z1": 33855,
      "z2": 40684,
      "type": "us"
    },
    {
      "z1": 33967,
      "z2": 40535,
      "type": "us"
    },
    {
      "z1": 34238,
      "z2": 40455,
      "type": "us"
    },
    {
      "z1": 34276,
      "z2": 40448,
      "type": "us"
    },
    {
      "z1": 34290,
      "z2": 40279,
      "type": "us"
    },
    {
      "z1": 34354,
      "z2": 40179,
      "type": "us"
    },
    {
      "z1": 34393,
      "z2": 40176,
      "type": "us"
    },
    {
      "z1": 34458,
      "z2": 40125,
      "type": "us"
    },
    {
      "z1": 34528,
      "z2": 40033,
      "type": "us"
    },
    {
      "z1": 34573,
      "z2": 40018,
      "type": "us"
    },
    {
      "z1": 34588,
      "z2": 39912,
      "type": "us"
    },
    {
      "z1": 34750,
      "z2": 39861,
      "type": "us"
    },
    {
      "z1": 34813,
      "z2": 39732,
      "type": "us"
    },
    {
      "z1": 34839,
      "z2": 39726,
      "type": "us"
    },
    {
      "z1": 34873,
      "z2": 39611,
      "type": "us"
    },
    {
      "z1": 34960,
      "z2": 39518,
      "type": "us"
    },
    {
      "z1": 35073,
      "z2": 39416,
      "type": "us"
    },
    {
      "z1": 35148,
      "z2": 39380,
      "type": "us"
    },
    {
      "z1": 35232,
      "z2": 39371,
      "type": "us"
    },
    {
      "z1": 35252,
      "z2": 39254,
      "type": "us"
    },
    {
      "z1": 35322,
      "z2": 39234,
      "type": "us"
    },
    {
      "z1": 35324,
      "z2": 39230,
      "type": "us"
    },
    {
      "z1": 35354,
      "z2": 39144,
      "type": "us"
    },
    {
      "z1": 35382,
      "z2": 39113,
      "type": "us"
    },
    {
      "z1": 35398,
      "z2": 39068,
      "type": "us"
    },
    {
      "z1": 35528,
      "z2": 38720,
      "type": "us"
    },
    {
      "z1": 35747,
      "z2": 38711,
      "type": "us"
    },
    {
      "z1": 35867,
      "z2": 38617,
      "type": "us"
    },
    {
      "z1": 35916,
      "z2": 38614,
      "type": "us"
    },
    {
      "z1": 35960,
      "z2": 38508,
      "type": "us"
    },
    {
      "z1": 36013,
      "z2": 38432,
      "type": "us"
    },
    {
      "z1": 36032,
      "z2": 38410,
      "type": "us"
    },
    {
      "z1": 36077,
      "z2": 38346,
      "type": "us"
    },
    {
      "z1": 36187,
      "z2": 38008,
      "type": "se"
    },
    {
      "z1": 36608,
      "z2": 37804,
      "type": "us"
    },
    {
      "z1": 36736,
      "z2": 37634,
      "type": "us"
    },
    {
      "z1": 36930,
      "z2": 37555,
      "type": "us"
    },
    {
      "z1": 37060,
      "z2": 37530,
      "type": "us"
    },
    {
      "z1": 37085,
      "z2": 37291,
      "type": "us"
    },
    {
      "z1": 37323,
      "z2": 37253,
      "type": "us"
    },
    {
      "z1": 37401,
      "z2": 37172,
      "type": "us"
    },
    {
      "z1": 37425,
      "z2": 37132,
      "type": "us"
    },
    {
      "z1": 37503,
      "z2": 37083,
      "type": "us"
    },
    {
      "z1": 37517,
      "z2": 36984,
      "type": "us"
    },
    {
      "z1": 37674,
      "z2": 36910,
      "type": "us"
    },
    {
      "z1": 37686,
      "z2": 36894,
      "type": "us"
    },
    {
      "z1": 37734,
      "z2": 36789,
      "type": "us"
    },
    {
      "z1": 37746,
      "z2": 36773,
      "type": "us"
    },
    {
      "z1": 37859,
      "z2": 36735,
      "type": "us"
    },
    {
      "z1": 37898,
      "z2": 36714,
      "type": "us"
    },
    {
      "z1": 37936,
      "z2": 36639,
      "type": "us"
    },
    {
      "z1": 37985,
      "z2": 36603,
      "type": "us"
    },
    {
      "z1": 37997,
      "z2": 36587,
      "type": "us"
    },
    {
      "z1": 38032,
      "z2": 36546,
      "type": "us"
    },
    {
      "z1": 38046,
      "z2": 36531,
      "type": "us"
    },
    {
      "z1": 38053,
      "z2": 36458,
      "type": "us"
    },
    {
      "z1": 38113,
      "z2": 36337,
      "type": "us"
    },
    {
      "z1": 38187,
      "z2": 36226,
      "type": "us"
    },
    {
      "z1": 38247,
      "z2": 36105,
      "type": "us"
    },
    {
      "z1": 38331,
      "z2": 36007,
      "type": "us"
    },
    {
      "z1": 38376,
      "z2": 35987,
      "type": "us"
    },
    {
      "z1": 38391,
      "z2": 35886,
      "type": "us"
    },
    {
      "z1": 38576,
      "z2": 35871,
      "type": "us"
    },
    {
      "z1": 38642,
      "z2": 35700,
      "type": "us"
    },
    {
      "z1": 38789,
      "z2": 35687,
      "type": "us"
    },
    {
      "z1": 38805,
      "z2": 35660,
      "type": "us"
    },
    {
      "z1": 38868,
      "z2": 35541,
      "type": "us"
    },
    {
      "z1": 38940,
      "z2": 35512,
      "type": "us"
    },
    {
      "z1": 38963,
      "z2": 35471,
      "type": "us"
    },
    {
      "z1": 39049,
      "z2": 35408,
      "type": "us"
    },
    {
      "z1": 39098,
      "z2": 35384,
      "type": "us"
    },
    {
      "z1": 39172,
      "z2": 35377,
      "type": "us"
    },
    {
      "z1": 39175,
      "z2": 35292,
      "type": "us"
    },
    {
      "z1": 39243,
      "z2": 35243,
      "type": "us"
    },
    {
      "z1": 39248,
      "z2": 35170,
      "type": "us"
    },
    {
      "z1": 39329,
      "z2": 35083,
      "type": "us"
    },
    {
      "z1": 39374,
      "z2": 35038,
      "type": "us"
    },
    {
      "z1": 39393,
      "z2": 34983,
      "type": "us"
    },
    {
      "z1": 39431,
      "z2": 34958,
      "type": "us"
    },
    {
      "z1": 39491,
      "z2": 34837,
      "type": "us"
    },
    {
      "z1": 39508,
      "z2": 34773,
      "type": "us"
    },
    {
      "z1": 39710,
      "z2": 34684,
      "type": "us"
    },
    {
      "z1": 39742,
      "z2": 34651,
      "type": "us"
    },
    {
      "z1": 39770,
      "z2": 34563,
      "type": "us"
    },
    {
      "z1": 39848,
      "z2": 34514,
      "type": "us"
    },
    {
      "z1": 39885,
      "z2": 34495,
      "type": "us"
    },
    {
      "z1": 39941,
      "z2": 34484,
      "type": "us"
    },
    {
      "z1": 39997,
      "z2": 34346,
      "type": "us"
    },
    {
      "z1": 40095,
      "z2": 34208,
      "type": "us"
    },
    {
      "z1": 40242,
      "z2": 34176,
      "type": "us"
    },
    {
      "z1": 40297,
      "z2": 34164,
      "type": "us"
    },
    {
      "z1": 40409,
      "z2": 34015,
      "type": "us"
    },
    {
      "z1": 40499,
      "z2": 33989,
      "type": "us"
    },
    {
      "z1": 40546,
      "z2": 33972,
      "type": "us"
    },
    {
      "z1": 40625,
      "z2": 33950,
      "type": "us"
    },
    {
      "z1": 40644,
      "z2": 33834,
      "type": "us"
    },
    {
      "z1": 40757,
      "z2": 33737,
      "type": "us"
    },
    {
      "z1": 40778,
      "z2": 33715,
      "type": "us"
    },
    {
      "z1": 40856,
      "z2": 33666,
      "type": "us"
    },
    {
      "z1": 40866,
      "z2": 33629,
      "type": "us"
    },
    {
      "z1": 40933,
      "z2": 33616,
      "type": "us"
    },
    {
      "z1": 40955,
      "z2": 33575,
      "type": "us"
    },
    {
      "z1": 40985,
      "z2": 33446,
      "type": "us"
    },
    {
      "z1": 41097,
      "z2": 33297,
      "type": "us"
    },
    {
      "z1": 41264,
      "z2": 33172,
      "type": "us"
    },
    {
      "z1": 41342,
      "z2": 33123,
      "type": "us"
    },
    {
      "z1": 41376,
      "z2": 33023,
      "type": "us"
    },
    {
      "z1": 41454,
      "z2": 32974,
      "type": "us"
    },
    {
      "z1": 41525,
      "z2": 32917,
      "type": "us"
    },
    {
      "z1": 41616,
      "z2": 32897,
      "type": "us"
    },
    {
      "z1": 41630,
      "z2": 32894,
      "type": "us"
    },
    {
      "z1": 41694,
      "z2": 32794,
      "type": "us"
    },
    {
      "z1": 41703,
      "z2": 32760,
      "type": "us"
    },
    {
      "z1": 41752,
      "z2": 32646,
      "type": "us"
    },
    {
      "z1": 41804,
      "z2": 32470,
      "type": "us"
    },
    {
      "z1": 41868,
      "z2": 32370,
      "type": "us"
    },
    {
      "z1": 42042,
      "z2": 32224,
      "type": "us"
    },
    {
      "z1": 42102,
      "z2": 32103,
      "type": "us"
    },
    {
      "z1": 42327,
      "z2": 31923,
      "type": "us"
    },
    {
      "z1": 42353,
      "z2": 31917,
      "type": "us"
    },
    {
      "z1": 42387,
      "z2": 31802,
      "type": "us"
    },
    {
      "z1": 42527,
      "z2": 31728,
      "type": "us"
    },
    {
      "z1": 42587,
      "z2": 31607,
      "type": "us"
    },
    {
      "z1": 42766,
      "z2": 31445,
      "type": "us"
    },
    {
      "z1": 42838,
      "z2": 31421,
      "type": "us"
    },
    {
      "z1": 43097,
      "z2": 31304,
      "type": "us"
    },
    {
      "z1": 43110,
      "z2": 31255,
      "type": "us"
    },
    {
      "z1": 43161,
      "z2": 31204,
      "type": "us"
    },
    {
      "z1": 43207,
      "z2": 31108,
      "type": "us"
    },
    {
      "z1": 43315,
      "z2": 31071,
      "type": "us"
    },
    {
      "z1": 43395,
      "z2": 30954,
      "type": "us"
    },
    {
      "z1": 43486,
      "z2": 30834,
      "type": "us"
    },
    {
      "z1": 43564,
      "z2": 30785,
      "type": "us"
    },
    {
      "z1": 43595,
      "z2": 30759,
      "type": "us"
    },
    {
      "z1": 43596,
      "z2": 30712,
      "type": "us"
    },
    {
      "z1": 43638,
      "z2": 30691,
      "type": "us"
    },
    {
      "z1": 43650,
      "z2": 30545,
      "type": "us"
    },
    {
      "z1": 43866,
      "z2": 30396,
      "type": "us"
    },
    {
      "z1": 43993,
      "z2": 30262,
      "type": "us"
    },
    {
      "z1": 44081,
      "z2": 30216,
      "type": "us"
    },
    {
      "z1": 44145,
      "z2": 30122,
      "type": "us"
    },
    {
      "z1": 44193,
      "z2": 30067,
      "type": "us"
    },
    {
      "z1": 44415,
      "z2": 30022,
      "type": "us"
    },
    {
      "z1": 44553,
      "z2": 29892,
      "type": "us"
    },
    {
      "z1": 44644,
      "z2": 29833,
      "type": "us"
    },
    {
      "z1": 44728,
      "z2": 29803,
      "type": "us"
    },
    {
      "z1": 44744,
      "z2": 29655,
      "type": "us"
    },
    {
      "z1": 44808,
      "z2": 29555,
      "type": "us"
    },
    {
      "z1": 44929,
      "z2": 29532,
      "type": "us"
    },
    {
      "z1": 44938,
      "z2": 29386,
      "type": "us"
    },
    {
      "z1": 45002,
      "z2": 29286,
      "type": "us"
    },
    {
      "z1": 45232,
      "z2": 29280,
      "type": "us"
    },
    {
      "z1": 45246,
      "z2": 29261,
      "type": "us"
    },
    {
      "z1": 45250,
      "z2": 29172,
      "type": "us"
    },
    {
      "z1": 45357,
      "z2": 29041,
      "type": "us"
    },
    {
      "z1": 45421,
      "z2": 28941,
      "type": "us"
    },
    {
      "z1": 45535,
      "z2": 28871,
      "type": "us"
    },
    {
      "z1": 45628,
      "z2": 28845,
      "type": "us"
    },
    {
      "z1": 45653,
      "z2": 28832,
      "type": "us"
    },
    {
      "z1": 45682,
      "z2": 28654,
      "type": "us"
    },
    {
      "z1": 45818,
      "z2": 28374,
      "type": "us"
    },
    {
      "z1": 45997,
      "z2": 28273,
      "type": "us"
    },
    {
      "z1": 46061,
      "z2": 28173,
      "type": "us"
    },
    {
      "z1": 46103,
      "z2": 28073,
      "type": "us"
    },
    {
      "z1": 46303,
      "z2": 27878,
      "type": "us"
    },
    {
      "z1": 46477,
      "z2": 27662,
      "type": "us"
    },
    {
      "z1": 46674,
      "z2": 27645,
      "type": "us"
    },
    {
      "z1": 46762,
      "z2": 27361,
      "type": "se"
    },
    {
      "z1": 46962,
      "z2": 27166,
      "type": "us"
    },
    {
      "z1": 47206,
      "z2": 27159,
      "type": "us"
    },
    {
      "z1": 47357,
      "z2": 27152,
      "type": "us"
    },
    {
      "z1": 47376,
      "z2": 26988,
      "type": "us"
    },
    {
      "z1": 47449,
      "z2": 26951,
      "type": "us"
    },
    {
      "z1": 47527,
      "z2": 26902,
      "type": "us"
    },
    {
      "z1": 47603,
      "z2": 26838,
      "type": "us"
    },
    {
      "z1": 47684,
      "z2": 26837,
      "type": "us"
    },
    {
      "z1": 47699,
      "z2": 26828,
      "type": "us"
    },
    {
      "z1": 47700,
      "z2": 26765,
      "type": "us"
    },
    {
      "z1": 47774,
      "z2": 26596,
      "type": "us"
    },
    {
      "z1": 47921,
      "z2": 26560,
      "type": "us"
    },
    {
      "z1": 47955,
      "z2": 26460,
      "type": "us"
    },
    {
      "z1": 48033,
      "z2": 26411,
      "type": "us"
    },
    {
      "z1": 48053,
      "z2": 26322,
      "type": "us"
    },
    {
      "z1": 48131,
      "z2": 26273,
      "type": "us"
    },
    {
      "z1": 48152,
      "z2": 26252,
      "type": "us"
    },
    {
      "z1": 48239,
      "z2": 26126,
      "type": "us"
    },
    {
      "z1": 48303,
      "z2": 26026,
      "type": "us"
    },
    {
      "z1": 48383,
      "z2": 25907,
      "type": "us"
    },
    {
      "z1": 48447,
      "z2": 25807,
      "type": "us"
    },
    {
      "z1": 48619,
      "z2": 25783,
      "type": "us"
    },
    {
      "z1": 48668,
      "z2": 25781,
      "type": "us"
    },
    {
      "z1": 48731,
      "z2": 25634,
      "type": "us"
    },
    {
      "z1": 48857,
      "z2": 25577,
      "type": "us"
    },
    {
      "z1": 48932,
      "z2": 25533,
      "type": "us"
    },
    {
      "z1": 48953,
      "z2": 25480,
      "type": "us"
    },
    {
      "z1": 48996,
      "z2": 25433,
      "type": "us"
    },
    {
      "z1": 49055,
      "z2": 25411,
      "type": "us"
    },
    {
      "z1": 49133,
      "z2": 25362,
      "type": "us"
    },
    {
      "z1": 49145,
      "z2": 25339,
      "type": "us"
    },
    {
      "z1": 49153,
      "z2": 25285,
      "type": "us"
    },
    {
      "z1": 49163,
      "z2": 25241,
      "type": "us"
    },
    {
      "z1": 49209,
      "z2": 25239,
      "type": "us"
    },
    {
      "z1": 49233,
      "z2": 25203,
      "type": "us"
    },
    {
      "z1": 49257,
      "z2": 25180,
      "type": "us"
    },
    {
      "z1": 49339,
      "z2": 25062,
      "type": "us"
    },
    {
      "z1": 49431,
      "z2": 25034,
      "type": "us"
    },
    {
      "z1": 49454,
      "z2": 25002,
      "type": "us"
    },
    {
      "z1": 49465,
      "z2": 24946,
      "type": "us"
    },
    {
      "z1": 49483,
      "z2": 24858,
      "type": "us"
    },
    {
      "z1": 49547,
      "z2": 24758,
      "type": "us"
    },
    {
      "z1": 49718,
      "z2": 24707,
      "type": "us"
    },
    {
      "z1": 49742,
      "z2": 24684,
      "type": "us"
    },
    {
      "z1": 49750,
      "z2": 24645,
      "type": "us"
    },
    {
      "z1": 49762,
      "z2": 24584,
      "type": "us"
    },
    {
      "z1": 49824,
      "z2": 24566,
      "type": "us"
    },
    {
      "z1": 49826,
      "z2": 24484,
      "type": "us"
    },
    {
      "z1": 49904,
      "z2": 24435,
      "type": "us"
    },
    {
      "z1": 49982,
      "z2": 24339,
      "type": "us"
    },
    {
      "z1": 50065,
      "z2": 24271,
      "type": "us"
    },
    {
      "z1": 50139,
      "z2": 24045,
      "type": "us"
    },
    {
      "z1": 50203,
      "z2": 23945,
      "type": "se"
    },
    {
      "z1": 50385,
      "z2": 23862,
      "type": "us"
    },
    {
      "z1": 50580,
      "z2": 23778,
      "type": "us"
    },
    {
      "z1": 50658,
      "z2": 23729,
      "type": "us"
    },
    {
      "z1": 50670,
      "z2": 23561,
      "type": "us"
    },
    {
      "z1": 50724,
      "z2": 23559,
      "type": "us"
    },
    {
      "z1": 50802,
      "z2": 23510,
      "type": "us"
    },
    {
      "z1": 50841,
      "z2": 23445,
      "type": "us"
    },
    {
      "z1": 50870,
      "z2": 23366,
      "type": "us"
    },
    {
      "z1": 51072,
      "z2": 23322,
      "type": "us"
    },
    {
      "z1": 51165,
      "z2": 23222,
      "type": "us"
    },
    {
      "z1": 51184,
      "z2": 23173,
      "type": "us"
    },
    {
      "z1": 51380,
      "z2": 23159,
      "type": "us"
    },
    {
      "z1": 51400,
      "z2": 23108,
      "type": "us"
    },
    {
      "z1": 51413,
      "z2": 23016,
      "type": "us"
    },
    {
      "z1": 51500,
      "z2": 22733,
      "type": "us"
    },
    {
      "z1": 51698,
      "z2": 22715,
      "type": "us"
    },
    {
      "z1": 51799,
      "z2": 22661,
      "type": "us"
    },
    {
      "z1": 51824,
      "z2": 22510,
      "type": "us"
    },
    {
      "z1": 51902,
      "z2": 22461,
      "type": "us"
    },
    {
      "z1": 51958,
      "z2": 22404,
      "type": "us"
    },
    {
      "z1": 51993,
      "z2": 22392,
      "type": "us"
    },
    {
      "z1": 52022,
      "z2": 22304,
      "type": "us"
    },
    {
      "z1": 52042,
      "z2": 22300,
      "type": "us"
    },
    {
      "z1": 52094,
      "z2": 22124,
      "type": "us"
    },
    {
      "z1": 52158,
      "z2": 22024,
      "type": "us"
    },
    {
      "z1": 52327,
      "z2": 21999,
      "type": "us"
    },
    {
      "z1": 52379,
      "z2": 21823,
      "type": "us"
    },
    {
      "z1": 52443,
      "z2": 21723,
      "type": "se"
    },
    {
      "z1": 52579,
      "z2": 21628,
      "type": "us"
    },
    {
      "z1": 52643,
      "z2": 21528,
      "type": "us"
    },
    {
      "z1": 52853,
      "z2": 21493,
      "type": "us"
    },
    {
      "z1": 52932,
      "z2": 21467,
      "type": "us"
    },
    {
      "z1": 52988,
      "z2": 21379,
      "type": "us"
    },
    {
      "z1": 53052,
      "z2": 21279,
      "type": "us"
    },
    {
      "z1": 53310,
      "z2": 21260,
      "type": "us"
    },
    {
      "z1": 53314,
      "z2": 21227,
      "type": "us"
    },
    {
      "z1": 53315,
      "z2": 21155,
      "type": "us"
    },
    {
      "z1": 53379,
      "z2": 21055,
      "type": "us"
    },
    {
      "z1": 53418,
      "z2": 20965,
      "type": "us"
    },
    {
      "z1": 53482,
      "z2": 20865,
      "type": "us"
    },
    {
      "z1": 53691,
      "z2": 20852,
      "type": "us"
    },
    {
      "z1": 53695,
      "z2": 20659,
      "type": "us"
    },
    {
      "z1": 53759,
      "z2": 20559,
      "type": "us"
    },
    {
      "z1": 54025,
      "z2": 20543,
      "type": "us"
    },
    {
      "z1": 54029,
      "z2": 20511,
      "type": "us"
    },
    {
      "z1": 54038,
      "z2": 20393,
      "type": "us"
    },
    {
      "z1": 54118,
      "z2": 20375,
      "type": "us"
    },
    {
      "z1": 54146,
      "z2": 20340,
      "type": "us"
    },
    {
      "z1": 54182,
      "z2": 20275,
      "type": "us"
    },
    {
      "z1": 54256,
      "z2": 20274,
      "type": "us"
    },
    {
      "z1": 54280,
      "z2": 20251,
      "type": "us"
    },
    {
      "z1": 54305,
      "z2": 20247,
      "type": "us"
    },
    {
      "z1": 54346,
      "z2": 20145,
      "type": "us"
    },
    {
      "z1": 54362,
      "z2": 20133,
      "type": "us"
    },
    {
      "z1": 54488,
      "z2": 19978,
      "type": "us"
    },
    {
      "z1": 54520,
      "z2": 19929,
      "type": "us"
    },
    {
      "z1": 54632,
      "z2": 19759,
      "type": "us"
    },
    {
      "z1": 54710,
      "z2": 19710,
      "type": "us"
    },
    {
      "z1": 54780,
      "z2": 19703,
      "type": "us"
    },
    {
      "z1": 54805,
      "z2": 19628,
      "type": "us"
    },
    {
      "z1": 54844,
      "z2": 19603,
      "type": "us"
    },
    {
      "z1": 54946,
      "z2": 19566,
      "type": "us"
    },
    {
      "z1": 55005,
      "z2": 19433,
      "type": "us"
    },
    {
      "z1": 55124,
      "z2": 19432,
      "type": "us"
    },
    {
      "z1": 55193,
      "z2": 19422,
      "type": "us"
    },
    {
      "z1": 55208,
      "z2": 19412,
      "type": "us"
    },
    {
      "z1": 55218,
      "z2": 19326,
      "type": "us"
    },
    {
      "z1": 55236,
      "z2": 19275,
      "type": "us"
    },
    {
      "z1": 55282,
      "z2": 19226,
      "type": "us"
    },
    {
      "z1": 55300,
      "z2": 19175,
      "type": "us"
    },
    {
      "z1": 55408,
      "z2": 18933,
      "type": "us"
    },
    {
      "z1": 55610,
      "z2": 18889,
      "type": "us"
    },
    {
      "z1": 55722,
      "z2": 18740,
      "type": "us"
    },
    {
      "z1": 55732,
      "z2": 18710,
      "type": "us"
    },
    {
      "z1": 55802,
      "z2": 18673,
      "type": "us"
    },
    {
      "z1": 55810,
      "z2": 18661,
      "type": "us"
    },
    {
      "z1": 55880,
      "z2": 18654,
      "type": "us"
    },
    {
      "z1": 55944,
      "z2": 18554,
      "type": "us"
    },
    {
      "z1": 56046,
      "z2": 18517,
      "type": "us"
    },
    {
      "z1": 56063,
      "z2": 18472,
      "type": "us"
    },
    {
      "z1": 56124,
      "z2": 18468,
      "type": "us"
    },
    {
      "z1": 56127,
      "z2": 18372,
      "type": "us"
    },
    {
      "z1": 56195,
      "z2": 18371,
      "type": "us"
    },
    {
      "z1": 56197,
      "z2": 18240,
      "type": "us"
    },
    {
      "z1": 56261,
      "z2": 18140,
      "type": "us"
    },
    {
      "z1": 56339,
      "z2": 18091,
      "type": "us"
    },
    {
      "z1": 56341,
      "z2": 18021,
      "type": "us"
    },
    {
      "z1": 56405,
      "z2": 17921,
      "type": "us"
    },
    {
      "z1": 56483,
      "z2": 17872,
      "type": "us"
    },
    {
      "z1": 56694,
      "z2": 17860,
      "type": "us"
    },
    {
      "z1": 56749,
      "z2": 17818,
      "type": "us"
    },
    {
      "z1": 56751,
      "z2": 17791,
      "type": "us"
    },
    {
      "z1": 56815,
      "z2": 17691,
      "type": "us"
    },
    {
      "z1": 56893,
      "z2": 17642,
      "type": "us"
    },
    {
      "z1": 56974,
      "z2": 17579,
      "type": "us"
    },
    {
      "z1": 57016,
      "z2": 17485,
      "type": "us"
    },
    {
      "z1": 57038,
      "z2": 17479,
      "type": "us"
    },
    {
      "z1": 57065,
      "z2": 17371,
      "type": "us"
    },
    {
      "z1": 57117,
      "z2": 17195,
      "type": "us"
    },
    {
      "z1": 57181,
      "z2": 17095,
      "type": "se"
    },
    {
      "z1": 57441,
      "z2": 16972,
      "type": "us"
    },
    {
      "z1": 57505,
      "z2": 16872,
      "type": "us"
    },
    {
      "z1": 57583,
      "z2": 16823,
      "type": "us"
    },
    {
      "z1": 57740,
      "z2": 16758,
      "type": "us"
    },
    {
      "z1": 57817,
      "z2": 16753,
      "type": "us"
    },
    {
      "z1": 57851,
      "z2": 16742,
      "type": "us"
    },
    {
      "z1": 57915,
      "z2": 16642,
      "type": "us"
    },
    {
      "z1": 57946,
      "z2": 16593,
      "type": "us"
    },
    {
      "z1": 58043,
      "z2": 16563,
      "type": "us"
    },
    {
      "z1": 58092,
      "z2": 16449,
      "type": "us"
    },
    {
      "z1": 58144,
      "z2": 16273,
      "type": "us"
    },
    {
      "z1": 58208,
      "z2": 16173,
      "type": "us"
    },
    {
      "z1": 58428,
      "z2": 16129,
      "type": "us"
    },
    {
      "z1": 58497,
      "z2": 16112,
      "type": "us"
    },
    {
      "z1": 58554,
      "z2": 16043,
      "type": "us"
    },
    {
      "z1": 58618,
      "z2": 15943,
      "type": "us"
    },
    {
      "z1": 58713,
      "z2": 15828,
      "type": "us"
    },
    {
      "z1": 58767,
      "z2": 15826,
      "type": "us"
    },
    {
      "z1": 58821,
      "z2": 15765,
      "type": "us"
    },
    {
      "z1": 58884,
      "z2": 15712,
      "type": "us"
    },
    {
      "z1": 58885,
      "z2": 15665,
      "type": "us"
    },
    {
      "z1": 58913,
      "z2": 15633,
      "type": "us"
    },
    {
      "z1": 58984,
      "z2": 15520,
      "type": "us"
    },
    {
      "z1": 59048,
      "z2": 15420,
      "type": "us"
    },
    {
      "z1": 59269,
      "z2": 15219,
      "type": "us"
    },
    {
      "z1": 59333,
      "z2": 15119,
      "type": "us"
    },
    {
      "z1": 59469,
      "z2": 15024,
      "type": "us"
    },
    {
      "z1": 59533,
      "z2": 14924,
      "type": "us"
    },
    {
      "z1": 59867,
      "z2": 14777,
      "type": "us"
    },
    {
      "z1": 59921,
      "z2": 14716,
      "type": "us"
    },
    {
      "z1": 59985,
      "z2": 14616,
      "type": "us"
    },
    {
      "z1": 60242,
      "z2": 14558,
      "type": "us"
    },
    {
      "z1": 60252,
      "z2": 14444,
      "type": "us"
    },
    {
      "z1": 60486,
      "z2": 14441,
      "type": "us"
    },
    {
      "z1": 60502,
      "z2": 14428,
      "type": "us"
    },
    {
      "z1": 60505,
      "z2": 14163,
      "type": "us"
    },
    {
      "z1": 60570,
      "z2": 14078,
      "type": "us"
    },
    {
      "z1": 60727,
      "z2": 14062,
      "type": "us"
    },
    {
      "z1": 60759,
      "z2": 14040,
      "type": "us"
    },
    {
      "z1": 60819,
      "z2": 13970,
      "type": "us"
    },
    {
      "z1": 60829,
      "z2": 13940,
      "type": "us"
    },
    {
      "z1": 60895,
      "z2": 13930,
      "type": "us"
    },
    {
      "z1": 60899,
      "z2": 13903,
      "type": "us"
    },
    {
      "z1": 60901,
      "z2": 13846,
      "type": "us"
    },
    {
      "z1": 60972,
      "z2": 13831,
      "type": "us"
    },
    {
      "z1": 61040,
      "z2": 13824,
      "type": "us"
    },
    {
      "z1": 61041,
      "z2": 13784,
      "type": "us"
    },
    {
      "z1": 61114,
      "z2": 13708,
      "type": "us"
    },
    {
      "z1": 61152,
      "z2": 13675,
      "type": "us"
    },
    {
      "z1": 61186,
      "z2": 13545,
      "type": "us"
    },
    {
      "z1": 61225,
      "z2": 13513,
      "type": "us"
    },
    {
      "z1": 61284,
      "z2": 13510,
      "type": "us"
    },
    {
      "z1": 61294,
      "z2": 13470,
      "type": "us"
    },
    {
      "z1": 61309,
      "z2": 13467,
      "type": "us"
    },
    {
      "z1": 61358,
      "z2": 13370,
      "type": "us"
    },
    {
      "z1": 61373,
      "z2": 13367,
      "type": "us"
    },
    {
      "z1": 61386,
      "z2": 13350,
      "type": "us"
    },
    {
      "z1": 61436,
      "z2": 13321,
      "type": "us"
    },
    {
      "z1": 61438,
      "z2": 13251,
      "type": "us"
    },
    {
      "z1": 61502,
      "z2": 13151,
      "type": "us"
    },
    {
      "z1": 61580,
      "z2": 13102,
      "type": "us"
    },
    {
      "z1": 61725,
      "z2": 12987,
      "type": "us"
    },
    {
      "z1": 61902,
      "z2": 12923,
      "type": "us"
    },
    {
      "z1": 61912,
      "z2": 12921,
      "type": "us"
    },
    {
      "z1": 61966,
      "z2": 12823,
      "type": "us"
    },
    {
      "z1": 62060,
      "z2": 12684,
      "type": "us"
    },
    {
      "z1": 62162,
      "z2": 12601,
      "type": "us"
    },
    {
      "z1": 62214,
      "z2": 12425,
      "type": "us"
    },
    {
      "z1": 62278,
      "z2": 12325,
      "type": "us"
    },
    {
      "z1": 62441,
      "z2": 12279,
      "type": "us"
    },
    {
      "z1": 62531,
      "z2": 12245,
      "type": "us"
    },
    {
      "z1": 62538,
      "z2": 12202,
      "type": "us"
    },
    {
      "z1": 62602,
      "z2": 12102,
      "type": "us"
    },
    {
      "z1": 62675,
      "z2": 12026,
      "type": "us"
    },
    {
      "z1": 62753,
      "z2": 11977,
      "type": "us"
    },
    {
      "z1": 62837,
      "z2": 11949,
      "type": "us"
    },
    {
      "z1": 62953,
      "z2": 11868,
      "type": "us"
    },
    {
      "z1": 62989,
      "z2": 11833,
      "type": "us"
    },
    {
      "z1": 63017,
      "z2": 11768,
      "type": "us"
    },
    {
      "z1": 63085,
      "z2": 11767,
      "type": "us"
    },
    {
      "z1": 63087,
      "z2": 11636,
      "type": "us"
    },
    {
      "z1": 63151,
      "z2": 11536,
      "type": "us"
    },
    {
      "z1": 63229,
      "z2": 11487,
      "type": "us"
    },
    {
      "z1": 63231,
      "z2": 11417,
      "type": "us"
    },
    {
      "z1": 63295,
      "z2": 11317,
      "type": "us"
    },
    {
      "z1": 63373,
      "z2": 11268,
      "type": "us"
    },
    {
      "z1": 63451,
      "z2": 11200,
      "type": "us"
    },
    {
      "z1": 63653,
      "z2": 11156,
      "type": "us"
    },
    {
      "z1": 63749,
      "z2": 11099,
      "type": "us"
    },
    {
      "z1": 63765,
      "z2": 11007,
      "type": "us"
    },
    {
      "z1": 63775,
      "z2": 10977,
      "type": "us"
    },
    {
      "z1": 63853,
      "z2": 10928,
      "type": "us"
    },
    {
      "z1": 64007,
      "z2": 10591,
      "type": "us"
    },
    {
      "z1": 64071,
      "z2": 10491,
      "type": "se"
    },
    {
      "z1": 64331,
      "z2": 10368,
      "type": "us"
    },
    {
      "z1": 64395,
      "z2": 10268,
      "type": "us"
    },
    {
      "z1": 64473,
      "z2": 10219,
      "type": "us"
    },
    {
      "z1": 64792,
      "z2": 10085,
      "type": "us"
    },
    {
      "z1": 64809,
      "z2": 10046,
      "type": "us"
    },
    {
      "z1": 64964,
      "z2": 10007,
      "type": "us"
    },
    {
      "z1": 65004,
      "z2": 9962,
      "type": "us"
    },
    {
      "z1": 65034,
      "z2": 9669,
      "type": "us"
    },
    {
      "z1": 65098,
      "z2": 9569,
      "type": "us"
    },
    {
      "z1": 65294,
      "z2": 9550,
      "type": "us"
    },
    {
      "z1": 65506,
      "z2": 9432,
      "type": "us"
    },
    {
      "z1": 65560,
      "z2": 9401,
      "type": "us"
    },
    {
      "z1": 65667,
      "z2": 9308,
      "type": "us"
    },
    {
      "z1": 65789,
      "z2": 9244,
      "type": "us"
    },
    {
      "z1": 65824,
      "z2": 9182,
      "type": "us"
    },
    {
      "z1": 65924,
      "z2": 8917,
      "type": "us"
    },
    {
      "z1": 66120,
      "z2": 8862,
      "type": "us"
    },
    {
      "z1": 66153,
      "z2": 8857,
      "type": "us"
    },
    {
      "z1": 66201,
      "z2": 8810,
      "type": "us"
    },
    {
      "z1": 66248,
      "z2": 8694,
      "type": "us"
    },
    {
      "z1": 66326,
      "z2": 8645,
      "type": "us"
    },
    {
      "z1": 66388,
      "z2": 8545,
      "type": "us"
    },
    {
      "z1": 66484,
      "z2": 8532,
      "type": "us"
    },
    {
      "z1": 66628,
      "z2": 8313,
      "type": "us"
    },
    {
      "z1": 66777,
      "z2": 8306,
      "type": "us"
    },
    {
      "z1": 66821,
      "z2": 8292,
      "type": "us"
    },
    {
      "z1": 66822,
      "z2": 8217,
      "type": "us"
    },
    {
      "z1": 66939,
      "z2": 8202,
      "type": "us"
    },
    {
      "z1": 66951,
      "z2": 7995,
      "type": "us"
    },
    {
      "z1": 67147,
      "z2": 7940,
      "type": "us"
    },
    {
      "z1": 67157,
      "z2": 7914,
      "type": "us"
    },
    {
      "z1": 67253,
      "z2": 7808,
      "type": "us"
    },
    {
      "z1": 67380,
      "z2": 7803,
      "type": "us"
    },
    {
      "z1": 67406,
      "z2": 7753,
      "type": "us"
    },
    {
      "z1": 67414,
      "z2": 7748,
      "type": "us"
    },
    {
      "z1": 67459,
      "z2": 7702,
      "type": "us"
    },
    {
      "z1": 67462,
      "z2": 7701,
      "type": "us"
    },
    {
      "z1": 67481,
      "z2": 7691,
      "type": "us"
    },
    {
      "z1": 67502,
      "z2": 7630,
      "type": "us"
    },
    {
      "z1": 67577,
      "z2": 7584,
      "type": "us"
    },
    {
      "z1": 67628,
      "z2": 7475,
      "type": "us"
    },
    {
      "z1": 67649,
      "z2": 7436,
      "type": "us"
    },
    {
      "z1": 67706,
      "z2": 7426,
      "type": "us"
    },
    {
      "z1": 67728,
      "z2": 7264,
      "type": "us"
    },
    {
      "z1": 67772,
      "z2": 7256,
      "type": "us"
    },
    {
      "z1": 67823,
      "z2": 7230,
      "type": "us"
    },
    {
      "z1": 67850,
      "z2": 7207,
      "type": "us"
    },
    {
      "z1": 67889,
      "z2": 7204,
      "type": "us"
    },
    {
      "z1": 67929,
      "z2": 7130,
      "type": "us"
    },
    {
      "z1": 68007,
      "z2": 7081,
      "type": "us"
    },
    {
      "z1": 68086,
      "z2": 7063,
      "type": "us"
    },
    {
      "z1": 68136,
      "z2": 7027,
      "type": "us"
    },
    {
      "z1": 68147,
      "z2": 7007,
      "type": "us"
    },
    {
      "z1": 68184,
      "z2": 6992,
      "type": "us"
    },
    {
      "z1": 68204,
      "z2": 6978,
      "type": "us"
    },
    {
      "z1": 68225,
      "z2": 6958,
      "type": "us"
    },
    {
      "z1": 68235,
      "z2": 6876,
      "type": "us"
    },
    {
      "z1": 68353,
      "z2": 6758,
      "type": "us"
    },
    {
      "z1": 68453,
      "z2": 6695,
      "type": "us"
    },
    {
      "z1": 68548,
      "z2": 6430,
      "type": "us"
    },
    {
      "z1": 68615,
      "z2": 6383,
      "type": "us"
    },
    {
      "z1": 68705,
      "z2": 6304,
      "type": "us"
    },
    {
      "z1": 68862,
      "z2": 6237,
      "type": "us"
    },
    {
      "z1": 68872,
      "z2": 6207,
      "type": "us"
    },
    {
      "z1": 68912,
      "z2": 6162,
      "type": "us"
    },
    {
      "z1": 68950,
      "z2": 6158,
      "type": "us"
    },
    {
      "z1": 68980,
      "z2": 6152,
      "type": "us"
    },
    {
      "z1": 68990,
      "z2": 6113,
      "type": "us"
    },
    {
      "z1": 69029,
      "z2": 6081,
      "type": "us"
    },
    {
      "z1": 69056,
      "z2": 5943,
      "type": "us"
    },
    {
      "z1": 69134,
      "z2": 5894,
      "type": "us"
    },
    {
      "z1": 69380,
      "z2": 5836,
      "type": "us"
    },
    {
      "z1": 69575,
      "z2": 5508,
      "type": "us"
    },
    {
      "z1": 69732,
      "z2": 5382,
      "type": "us"
    },
    {
      "z1": 69832,
      "z2": 5117,
      "type": "se"
    },
    {
      "z1": 70084,
      "z2": 5097,
      "type": "us"
    },
    {
      "z1": 70156,
      "z2": 4894,
      "type": "us"
    },
    {
      "z1": 70234,
      "z2": 4845,
      "type": "us"
    },
    {
      "z1": 70603,
      "z2": 4662,
      "type": "us"
    },
    {
      "z1": 70760,
      "z2": 4536,
      "type": "us"
    },
    {
      "z1": 70859,
      "z2": 4195,
      "type": "se"
    },
    {
      "z1": 71184,
      "z2": 4048,
      "type": "us"
    },
    {
      "z1": 71262,
      "z2": 3999,
      "type": "us"
    },
    {
      "z1": 71829,
      "z2": 3896,
      "type": "us"
    },
    {
      "z1": 71887,
      "z2": 3349,
      "type": "se"
    },
    {
      "z1": 72706,
      "z2": 3267,
      "type": "us"
    },
    {
      "z1": 72784,
      "z2": 3218,
      "type": "us"
    },
    {
      "z1": 73205,
      "z2": 2933,
      "type": "us"
    },
    {
      "z1": 73409,
      "z2": 2568,
      "type": "se"
    },
    {
      "z1": 74323,
      "z2": 2534,
      "type": "se"
    }
  ]
}
