{
  "contributionName": "Pedersen08",
  "objectives": 2,
  "objectiveType": ["int", "int"],
  "direction": ["min", "min"],
  "comments": "Results from the paper by Pedersen et. al (2008)",
  "optimal": true,
  "cpu": {
    "sec": 0,
    "machineSpec": "Intel Xeon 2.67 GHz, 6 GB RAM, Red Hat Enterprise Linux v4.0 OS"
  },
  "valid": true,
  "version": "1.0",
  "instanceName": "Pedersen08_MMAP_d4_e2-8_c0-10000_m1_s60_39",
  "suppCard": 13,
  "extCard": 13,
  "card": 46,
  "points": [
    {
      "z1": 1236,
      "z2": 33212,
      "type": "se"
    },
    {
      "z1": 1344,
      "z2": 30941,
      "type": "se"
    },
    {
      "z1": 1607,
      "z2": 30594,
      "type": "us"
    },
    {
      "z1": 1690,
      "z2": 30072,
      "type": "us"
    },
    {
      "z1": 1715,
      "z2": 28323,
      "type": "se"
    },
    {
      "z1": 2066,
      "z2": 28314,
      "type": "us"
    },
    {
      "z1": 2134,
      "z2": 26971,
      "type": "us"
    },
    {
      "z1": 2174,
      "z2": 26043,
      "type": "us"
    },
    {
      "z1": 2505,
      "z2": 24353,
      "type": "se"
    },
    {
      "z1": 3102,
      "z2": 24319,
      "type": "us"
    },
    {
      "z1": 3365,
      "z2": 23168,
      "type": "us"
    },
    {
      "z1": 3384,
      "z2": 22760,
      "type": "us"
    },
    {
      "z1": 3473,
      "z2": 21701,
      "type": "se"
    },
    {
      "z1": 3696,
      "z2": 21478,
      "type": "us"
    },
    {
      "z1": 4158,
      "z2": 20400,
      "type": "us"
    },
    {
      "z1": 4352,
      "z2": 20108,
      "type": "us"
    },
    {
      "z1": 4664,
      "z2": 18826,
      "type": "se"
    },
    {
      "z1": 5126,
      "z2": 17748,
      "type": "se"
    },
    {
      "z1": 5892,
      "z2": 16963,
      "type": "us"
    },
    {
      "z1": 6268,
      "z2": 16764,
      "type": "us"
    },
    {
      "z1": 6289,
      "z2": 16295,
      "type": "us"
    },
    {
      "z1": 6730,
      "z2": 15686,
      "type": "us"
    },
    {
      "z1": 6751,
      "z2": 15217,
      "type": "us"
    },
    {
      "z1": 7236,
      "z2": 14112,
      "type": "us"
    },
    {
      "z1": 7698,
      "z2": 13034,
      "type": "se"
    },
    {
      "z1": 8464,
      "z2": 12249,
      "type": "se"
    },
    {
      "z1": 11057,
      "z2": 11724,
      "type": "us"
    },
    {
      "z1": 11823,
      "z2": 10939,
      "type": "us"
    },
    {
      "z1": 13990,
      "z2": 10737,
      "type": "us"
    },
    {
      "z1": 14011,
      "z2": 10268,
      "type": "us"
    },
    {
      "z1": 14496,
      "z2": 9163,
      "type": "us"
    },
    {
      "z1": 14958,
      "z2": 8085,
      "type": "us"
    },
    {
      "z1": 15724,
      "z2": 7300,
      "type": "se"
    },
    {
      "z1": 18317,
      "z2": 6775,
      "type": "us"
    },
    {
      "z1": 19083,
      "z2": 5990,
      "type": "us"
    },
    {
      "z1": 21804,
      "z2": 5844,
      "type": "us"
    },
    {
      "z1": 22552,
      "z2": 5514,
      "type": "us"
    },
    {
      "z1": 23021,
      "z2": 5487,
      "type": "us"
    },
    {
      "z1": 23399,
      "z2": 5299,
      "type": "us"
    },
    {
      "z1": 23522,
      "z2": 4719,
      "type": "us"
    },
    {
      "z1": 23787,
      "z2": 4702,
      "type": "us"
    },
    {
      "z1": 23861,
      "z2": 4221,
      "type": "us"
    },
    {
      "z1": 24627,
      "z2": 3436,
      "type": "se"
    },
    {
      "z1": 26371,
      "z2": 3224,
      "type": "us"
    },
    {
      "z1": 29066,
      "z2": 2165,
      "type": "se"
    },
    {
      "z1": 31650,
      "z2": 1836,
      "type": "se"
    }
  ]
}
