<?xml version="1.0" encoding="ISO-8859-1"?>
<!--Assignment problem matrix for the bicriterion (multi modual) AP problem generated using the APMatGen generator
Christian Roed Pedersen and Lars Relund Nielsen (c)-->
<apmat dimension="4" version="1.0" costrange="1-10000" entryrange="2-8" seed="193241">
    <cell row="0" column="0" entries="8">
        <entry c1="5" c2="9744"/>
        <entry c1="664" c2="9473"/>
        <entry c1="1348" c2="9178"/>
        <entry c1="1913" c2="9045"/>
        <entry c1="1939" c2="8718"/>
        <entry c1="2373" c2="7940"/>
        <entry c1="2796" c2="7308"/>
        <entry c1="3662" c2="6366"/>
    </cell>
    <cell row="0" column="1" entries="2">
        <entry c1="5294" c2="3495"/>
        <entry c1="9467" c2="2148"/>
    </cell>
    <cell row="0" column="2" entries="7">
        <entry c1="616" c2="9355"/>
        <entry c1="1323" c2="9174"/>
        <entry c1="1797" c2="9142"/>
        <entry c1="2089" c2="8680"/>
        <entry c1="2619" c2="7784"/>
        <entry c1="3044" c2="7626"/>
        <entry c1="4222" c2="5612"/>
    </cell>
    <cell row="0" column="3" entries="7">
        <entry c1="5560" c2="4580"/>
        <entry c1="5567" c2="4116"/>
        <entry c1="6309" c2="3486"/>
        <entry c1="6945" c2="2976"/>
        <entry c1="7293" c2="2474"/>
        <entry c1="7361" c2="2095"/>
        <entry c1="7929" c2="235"/>
    </cell>
    <cell row="1" column="0" entries="3">
        <entry c1="262" c2="9498"/>
        <entry c1="683" c2="7690"/>
        <entry c1="920" c2="5139"/>
    </cell>
    <cell row="1" column="1" entries="3">
        <entry c1="5287" c2="3389"/>
        <entry c1="6026" c2="2479"/>
        <entry c1="8910" c2="114"/>
    </cell>
    <cell row="1" column="2" entries="2">
        <entry c1="648" c2="8367"/>
        <entry c1="1535" c2="7392"/>
    </cell>
    <cell row="1" column="3" entries="2">
        <entry c1="6258" c2="4220"/>
        <entry c1="6614" c2="3845"/>
    </cell>
    <cell row="2" column="0" entries="4">
        <entry c1="878" c2="8845"/>
        <entry c1="1619" c2="7575"/>
        <entry c1="2458" c2="6509"/>
        <entry c1="4670" c2="5750"/>
    </cell>
    <cell row="2" column="1" entries="5">
        <entry c1="5748" c2="4847"/>
        <entry c1="6189" c2="3652"/>
        <entry c1="6340" c2="2691"/>
        <entry c1="7616" c2="1690"/>
        <entry c1="7740" c2="633"/>
    </cell>
    <cell row="2" column="2" entries="2">
        <entry c1="171" c2="8280"/>
        <entry c1="293" c2="6082"/>
    </cell>
    <cell row="2" column="3" entries="2">
        <entry c1="5092" c2="4596"/>
        <entry c1="9281" c2="2887"/>
    </cell>
    <cell row="3" column="0" entries="2">
        <entry c1="2109" c2="9102"/>
        <entry c1="3480" c2="7975"/>
    </cell>
    <cell row="3" column="1" entries="4">
        <entry c1="5567" c2="4004"/>
        <entry c1="6242" c2="3619"/>
        <entry c1="7669" c2="1812"/>
        <entry c1="9970" c2="34"/>
    </cell>
    <cell row="3" column="2" entries="2">
        <entry c1="2050" c2="8817"/>
        <entry c1="4365" c2="5564"/>
    </cell>
    <cell row="3" column="3" entries="4">
        <entry c1="6176" c2="4227"/>
        <entry c1="7155" c2="4171"/>
        <entry c1="8310" c2="2111"/>
        <entry c1="9802" c2="335"/>
    </cell>
</apmat>
