<?xml version="1.0" encoding="ISO-8859-1"?>
<!--Assignment problem matrix for the bicriterion (multi modual) AP problem generated using the APMatGen generator
Christian Roed Pedersen and Lars Relund Nielsen (c)-->
<apmat dimension="4" version="1.0" costrange="1-500" entryrange="2-8" seed="278625">
    <cell row="0" column="0" entries="3">
        <entry c1="27" c2="432"/>
        <entry c1="67" c2="365"/>
        <entry c1="177" c2="347"/>
    </cell>
    <cell row="0" column="1" entries="3">
        <entry c1="306" c2="230"/>
        <entry c1="355" c2="131"/>
        <entry c1="429" c2="0"/>
    </cell>
    <cell row="0" column="2" entries="3">
        <entry c1="80" c2="485"/>
        <entry c1="152" c2="383"/>
        <entry c1="153" c2="327"/>
    </cell>
    <cell row="0" column="3" entries="6">
        <entry c1="273" c2="234"/>
        <entry c1="279" c2="207"/>
        <entry c1="307" c2="196"/>
        <entry c1="340" c2="145"/>
        <entry c1="380" c2="121"/>
        <entry c1="490" c2="71"/>
    </cell>
    <cell row="1" column="0" entries="4">
        <entry c1="16" c2="473"/>
        <entry c1="75" c2="426"/>
        <entry c1="111" c2="422"/>
        <entry c1="131" c2="335"/>
    </cell>
    <cell row="1" column="1" entries="6">
        <entry c1="284" c2="209"/>
        <entry c1="312" c2="200"/>
        <entry c1="353" c2="154"/>
        <entry c1="400" c2="128"/>
        <entry c1="418" c2="108"/>
        <entry c1="459" c2="82"/>
    </cell>
    <cell row="1" column="2" entries="5">
        <entry c1="15" c2="496"/>
        <entry c1="25" c2="476"/>
        <entry c1="76" c2="433"/>
        <entry c1="144" c2="396"/>
        <entry c1="239" c2="352"/>
    </cell>
    <cell row="1" column="3" entries="6">
        <entry c1="268" c2="221"/>
        <entry c1="283" c2="211"/>
        <entry c1="312" c2="190"/>
        <entry c1="332" c2="153"/>
        <entry c1="361" c2="113"/>
        <entry c1="461" c2="89"/>
    </cell>
    <cell row="2" column="0" entries="3">
        <entry c1="81" c2="482"/>
        <entry c1="142" c2="370"/>
        <entry c1="240" c2="252"/>
    </cell>
    <cell row="2" column="1" entries="6">
        <entry c1="263" c2="212"/>
        <entry c1="311" c2="211"/>
        <entry c1="322" c2="158"/>
        <entry c1="367" c2="125"/>
        <entry c1="399" c2="106"/>
        <entry c1="408" c2="54"/>
    </cell>
    <cell row="2" column="2" entries="2">
        <entry c1="72" c2="400"/>
        <entry c1="183" c2="318"/>
    </cell>
    <cell row="2" column="3" entries="4">
        <entry c1="307" c2="208"/>
        <entry c1="314" c2="140"/>
        <entry c1="406" c2="91"/>
        <entry c1="416" c2="39"/>
    </cell>
    <cell row="3" column="0" entries="7">
        <entry c1="34" c2="484"/>
        <entry c1="45" c2="455"/>
        <entry c1="75" c2="443"/>
        <entry c1="99" c2="438"/>
        <entry c1="146" c2="427"/>
        <entry c1="184" c2="376"/>
        <entry c1="243" c2="287"/>
    </cell>
    <cell row="3" column="1" entries="2">
        <entry c1="369" c2="158"/>
        <entry c1="487" c2="108"/>
    </cell>
    <cell row="3" column="2" entries="6">
        <entry c1="36" c2="478"/>
        <entry c1="62" c2="473"/>
        <entry c1="99" c2="446"/>
        <entry c1="141" c2="441"/>
        <entry c1="164" c2="385"/>
        <entry c1="165" c2="372"/>
    </cell>
    <cell row="3" column="3" entries="5">
        <entry c1="274" c2="238"/>
        <entry c1="294" c2="191"/>
        <entry c1="338" c2="175"/>
        <entry c1="393" c2="158"/>
        <entry c1="460" c2="22"/>
    </cell>
</apmat>
