{
  "contributionName": "Pedersen08",
  "objectives": 2,
  "objectiveType": ["int", "int"],
  "direction": ["min", "min"],
  "comments": "Results from the paper by Pedersen et. al (2008)",
  "optimal": true,
  "cpu": {
    "sec": 0.84,
    "machineSpec": "Intel Xeon 2.67 GHz, 6 GB RAM, Red Hat Enterprise Linux v4.0 OS"
  },
  "valid": true,
  "version": "1.0",
  "instanceName": "Pedersen08_AP_d20_c0-1000_88",
  "suppCard": 28,
  "extCard": 27,
  "card": 626,
  "points": [
    {
      "z1": 1356,
      "z2": 19375,
      "type": "se"
    },
    {
      "z1": 1357,
      "z2": 19303,
      "type": "se"
    },
    {
      "z1": 1368,
      "z2": 19295,
      "type": "us"
    },
    {
      "z1": 1387,
      "z2": 19180,
      "type": "se"
    },
    {
      "z1": 1407,
      "z2": 19143,
      "type": "us"
    },
    {
      "z1": 1464,
      "z2": 19134,
      "type": "us"
    },
    {
      "z1": 1467,
      "z2": 19124,
      "type": "us"
    },
    {
      "z1": 1483,
      "z2": 19122,
      "type": "us"
    },
    {
      "z1": 1487,
      "z2": 19087,
      "type": "us"
    },
    {
      "z1": 1502,
      "z2": 19025,
      "type": "us"
    },
    {
      "z1": 1506,
      "z2": 19021,
      "type": "us"
    },
    {
      "z1": 1518,
      "z2": 18986,
      "type": "us"
    },
    {
      "z1": 1534,
      "z2": 18953,
      "type": "us"
    },
    {
      "z1": 1572,
      "z2": 18937,
      "type": "us"
    },
    {
      "z1": 1592,
      "z2": 18917,
      "type": "us"
    },
    {
      "z1": 1603,
      "z2": 18909,
      "type": "us"
    },
    {
      "z1": 1614,
      "z2": 18897,
      "type": "us"
    },
    {
      "z1": 1642,
      "z2": 18878,
      "type": "us"
    },
    {
      "z1": 1649,
      "z2": 18858,
      "type": "us"
    },
    {
      "z1": 1654,
      "z2": 18843,
      "type": "us"
    },
    {
      "z1": 1669,
      "z2": 18821,
      "type": "us"
    },
    {
      "z1": 1671,
      "z2": 18815,
      "type": "us"
    },
    {
      "z1": 1691,
      "z2": 18795,
      "type": "us"
    },
    {
      "z1": 1702,
      "z2": 18738,
      "type": "us"
    },
    {
      "z1": 1718,
      "z2": 18654,
      "type": "us"
    },
    {
      "z1": 1728,
      "z2": 18347,
      "type": "se"
    },
    {
      "z1": 1785,
      "z2": 18338,
      "type": "us"
    },
    {
      "z1": 1823,
      "z2": 18229,
      "type": "us"
    },
    {
      "z1": 1827,
      "z2": 18225,
      "type": "us"
    },
    {
      "z1": 1855,
      "z2": 18157,
      "type": "us"
    },
    {
      "z1": 1924,
      "z2": 18150,
      "type": "us"
    },
    {
      "z1": 1934,
      "z2": 18118,
      "type": "us"
    },
    {
      "z1": 1943,
      "z2": 18104,
      "type": "us"
    },
    {
      "z1": 1948,
      "z2": 18101,
      "type": "us"
    },
    {
      "z1": 1963,
      "z2": 18082,
      "type": "us"
    },
    {
      "z1": 1987,
      "z2": 18061,
      "type": "us"
    },
    {
      "z1": 1990,
      "z2": 18025,
      "type": "us"
    },
    {
      "z1": 1996,
      "z2": 18017,
      "type": "us"
    },
    {
      "z1": 2031,
      "z2": 18003,
      "type": "us"
    },
    {
      "z1": 2038,
      "z2": 17986,
      "type": "us"
    },
    {
      "z1": 2045,
      "z2": 17963,
      "type": "us"
    },
    {
      "z1": 2068,
      "z2": 17912,
      "type": "us"
    },
    {
      "z1": 2079,
      "z2": 17907,
      "type": "us"
    },
    {
      "z1": 2089,
      "z2": 17903,
      "type": "us"
    },
    {
      "z1": 2109,
      "z2": 17788,
      "type": "us"
    },
    {
      "z1": 2140,
      "z2": 17770,
      "type": "us"
    },
    {
      "z1": 2160,
      "z2": 17646,
      "type": "us"
    },
    {
      "z1": 2194,
      "z2": 17634,
      "type": "us"
    },
    {
      "z1": 2198,
      "z2": 17538,
      "type": "us"
    },
    {
      "z1": 2200,
      "z2": 17497,
      "type": "us"
    },
    {
      "z1": 2216,
      "z2": 17456,
      "type": "us"
    },
    {
      "z1": 2251,
      "z2": 17453,
      "type": "us"
    },
    {
      "z1": 2252,
      "z2": 17381,
      "type": "us"
    },
    {
      "z1": 2263,
      "z2": 17373,
      "type": "us"
    },
    {
      "z1": 2285,
      "z2": 17293,
      "type": "us"
    },
    {
      "z1": 2317,
      "z2": 17221,
      "type": "us"
    },
    {
      "z1": 2331,
      "z2": 17204,
      "type": "us"
    },
    {
      "z1": 2362,
      "z2": 17202,
      "type": "us"
    },
    {
      "z1": 2378,
      "z2": 17200,
      "type": "us"
    },
    {
      "z1": 2386,
      "z2": 17181,
      "type": "us"
    },
    {
      "z1": 2404,
      "z2": 17169,
      "type": "us"
    },
    {
      "z1": 2408,
      "z2": 17165,
      "type": "us"
    },
    {
      "z1": 2410,
      "z2": 17128,
      "type": "us"
    },
    {
      "z1": 2421,
      "z2": 17114,
      "type": "us"
    },
    {
      "z1": 2447,
      "z2": 17090,
      "type": "us"
    },
    {
      "z1": 2462,
      "z2": 17010,
      "type": "us"
    },
    {
      "z1": 2493,
      "z2": 17008,
      "type": "us"
    },
    {
      "z1": 2530,
      "z2": 16976,
      "type": "us"
    },
    {
      "z1": 2547,
      "z2": 16971,
      "type": "us"
    },
    {
      "z1": 2560,
      "z2": 16817,
      "type": "us"
    },
    {
      "z1": 2603,
      "z2": 16723,
      "type": "us"
    },
    {
      "z1": 2616,
      "z2": 16641,
      "type": "us"
    },
    {
      "z1": 2650,
      "z2": 16611,
      "type": "us"
    },
    {
      "z1": 2669,
      "z2": 16556,
      "type": "us"
    },
    {
      "z1": 2682,
      "z2": 16539,
      "type": "us"
    },
    {
      "z1": 2701,
      "z2": 16484,
      "type": "us"
    },
    {
      "z1": 2756,
      "z2": 16412,
      "type": "us"
    },
    {
      "z1": 2767,
      "z2": 16404,
      "type": "us"
    },
    {
      "z1": 2769,
      "z2": 16394,
      "type": "us"
    },
    {
      "z1": 2787,
      "z2": 16340,
      "type": "us"
    },
    {
      "z1": 2798,
      "z2": 16332,
      "type": "us"
    },
    {
      "z1": 2828,
      "z2": 16306,
      "type": "us"
    },
    {
      "z1": 2851,
      "z2": 16250,
      "type": "us"
    },
    {
      "z1": 2866,
      "z2": 16233,
      "type": "us"
    },
    {
      "z1": 2883,
      "z2": 16178,
      "type": "us"
    },
    {
      "z1": 2913,
      "z2": 16159,
      "type": "us"
    },
    {
      "z1": 2928,
      "z2": 16142,
      "type": "us"
    },
    {
      "z1": 2945,
      "z2": 16087,
      "type": "us"
    },
    {
      "z1": 2982,
      "z2": 16049,
      "type": "us"
    },
    {
      "z1": 3018,
      "z2": 16044,
      "type": "us"
    },
    {
      "z1": 3029,
      "z2": 16038,
      "type": "us"
    },
    {
      "z1": 3032,
      "z2": 15967,
      "type": "us"
    },
    {
      "z1": 3048,
      "z2": 15926,
      "type": "us"
    },
    {
      "z1": 3074,
      "z2": 15842,
      "type": "us"
    },
    {
      "z1": 3085,
      "z2": 15834,
      "type": "us"
    },
    {
      "z1": 3088,
      "z2": 15791,
      "type": "us"
    },
    {
      "z1": 3104,
      "z2": 15750,
      "type": "us"
    },
    {
      "z1": 3121,
      "z2": 15730,
      "type": "us"
    },
    {
      "z1": 3132,
      "z2": 15722,
      "type": "us"
    },
    {
      "z1": 3148,
      "z2": 15691,
      "type": "us"
    },
    {
      "z1": 3163,
      "z2": 15674,
      "type": "us"
    },
    {
      "z1": 3173,
      "z2": 15646,
      "type": "us"
    },
    {
      "z1": 3180,
      "z2": 15619,
      "type": "us"
    },
    {
      "z1": 3189,
      "z2": 15605,
      "type": "us"
    },
    {
      "z1": 3204,
      "z2": 15515,
      "type": "us"
    },
    {
      "z1": 3219,
      "z2": 15498,
      "type": "us"
    },
    {
      "z1": 3236,
      "z2": 15443,
      "type": "se"
    },
    {
      "z1": 3258,
      "z2": 15442,
      "type": "us"
    },
    {
      "z1": 3273,
      "z2": 15425,
      "type": "us"
    },
    {
      "z1": 3290,
      "z2": 15370,
      "type": "us"
    },
    {
      "z1": 3359,
      "z2": 15330,
      "type": "us"
    },
    {
      "z1": 3384,
      "z2": 15314,
      "type": "us"
    },
    {
      "z1": 3413,
      "z2": 15300,
      "type": "us"
    },
    {
      "z1": 3419,
      "z2": 15272,
      "type": "us"
    },
    {
      "z1": 3421,
      "z2": 15260,
      "type": "us"
    },
    {
      "z1": 3449,
      "z2": 15198,
      "type": "us"
    },
    {
      "z1": 3472,
      "z2": 15196,
      "type": "us"
    },
    {
      "z1": 3473,
      "z2": 15191,
      "type": "us"
    },
    {
      "z1": 3480,
      "z2": 15151,
      "type": "us"
    },
    {
      "z1": 3503,
      "z2": 15125,
      "type": "us"
    },
    {
      "z1": 3528,
      "z2": 15116,
      "type": "us"
    },
    {
      "z1": 3544,
      "z2": 15115,
      "type": "us"
    },
    {
      "z1": 3545,
      "z2": 15106,
      "type": "us"
    },
    {
      "z1": 3546,
      "z2": 15044,
      "type": "us"
    },
    {
      "z1": 3552,
      "z2": 15025,
      "type": "us"
    },
    {
      "z1": 3576,
      "z2": 14872,
      "type": "us"
    },
    {
      "z1": 3591,
      "z2": 14855,
      "type": "us"
    },
    {
      "z1": 3608,
      "z2": 14800,
      "type": "us"
    },
    {
      "z1": 3623,
      "z2": 14760,
      "type": "us"
    },
    {
      "z1": 3638,
      "z2": 14743,
      "type": "us"
    },
    {
      "z1": 3655,
      "z2": 14688,
      "type": "se"
    },
    {
      "z1": 3738,
      "z2": 14636,
      "type": "us"
    },
    {
      "z1": 3753,
      "z2": 14619,
      "type": "us"
    },
    {
      "z1": 3777,
      "z2": 14598,
      "type": "us"
    },
    {
      "z1": 3786,
      "z2": 14578,
      "type": "us"
    },
    {
      "z1": 3792,
      "z2": 14563,
      "type": "us"
    },
    {
      "z1": 3794,
      "z2": 14533,
      "type": "us"
    },
    {
      "z1": 3819,
      "z2": 14517,
      "type": "us"
    },
    {
      "z1": 3824,
      "z2": 14510,
      "type": "us"
    },
    {
      "z1": 3868,
      "z2": 14443,
      "type": "us"
    },
    {
      "z1": 3879,
      "z2": 14388,
      "type": "us"
    },
    {
      "z1": 3904,
      "z2": 14372,
      "type": "us"
    },
    {
      "z1": 3956,
      "z2": 14348,
      "type": "us"
    },
    {
      "z1": 3968,
      "z2": 14260,
      "type": "us"
    },
    {
      "z1": 3993,
      "z2": 14249,
      "type": "us"
    },
    {
      "z1": 4004,
      "z2": 14201,
      "type": "us"
    },
    {
      "z1": 4019,
      "z2": 14184,
      "type": "us"
    },
    {
      "z1": 4036,
      "z2": 14129,
      "type": "us"
    },
    {
      "z1": 4089,
      "z2": 14039,
      "type": "us"
    },
    {
      "z1": 4110,
      "z2": 13993,
      "type": "us"
    },
    {
      "z1": 4125,
      "z2": 13976,
      "type": "us"
    },
    {
      "z1": 4142,
      "z2": 13970,
      "type": "us"
    },
    {
      "z1": 4157,
      "z2": 13881,
      "type": "us"
    },
    {
      "z1": 4172,
      "z2": 13864,
      "type": "us"
    },
    {
      "z1": 4212,
      "z2": 13836,
      "type": "us"
    },
    {
      "z1": 4226,
      "z2": 13745,
      "type": "us"
    },
    {
      "z1": 4241,
      "z2": 13728,
      "type": "us"
    },
    {
      "z1": 4280,
      "z2": 13672,
      "type": "us"
    },
    {
      "z1": 4295,
      "z2": 13655,
      "type": "us"
    },
    {
      "z1": 4337,
      "z2": 13631,
      "type": "us"
    },
    {
      "z1": 4366,
      "z2": 13594,
      "type": "us"
    },
    {
      "z1": 4375,
      "z2": 13593,
      "type": "us"
    },
    {
      "z1": 4406,
      "z2": 13565,
      "type": "us"
    },
    {
      "z1": 4411,
      "z2": 13562,
      "type": "us"
    },
    {
      "z1": 4420,
      "z2": 13521,
      "type": "us"
    },
    {
      "z1": 4438,
      "z2": 13498,
      "type": "us"
    },
    {
      "z1": 4458,
      "z2": 13456,
      "type": "us"
    },
    {
      "z1": 4481,
      "z2": 13453,
      "type": "us"
    },
    {
      "z1": 4483,
      "z2": 13440,
      "type": "us"
    },
    {
      "z1": 4504,
      "z2": 13378,
      "type": "us"
    },
    {
      "z1": 4508,
      "z2": 13353,
      "type": "us"
    },
    {
      "z1": 4538,
      "z2": 13322,
      "type": "us"
    },
    {
      "z1": 4551,
      "z2": 13266,
      "type": "us"
    },
    {
      "z1": 4555,
      "z2": 13241,
      "type": "us"
    },
    {
      "z1": 4598,
      "z2": 13102,
      "type": "us"
    },
    {
      "z1": 4613,
      "z2": 13085,
      "type": "us"
    },
    {
      "z1": 4630,
      "z2": 13079,
      "type": "us"
    },
    {
      "z1": 4645,
      "z2": 12990,
      "type": "se"
    },
    {
      "z1": 4660,
      "z2": 12973,
      "type": "us"
    },
    {
      "z1": 4702,
      "z2": 12949,
      "type": "us"
    },
    {
      "z1": 4715,
      "z2": 12934,
      "type": "us"
    },
    {
      "z1": 4767,
      "z2": 12900,
      "type": "us"
    },
    {
      "z1": 4776,
      "z2": 12880,
      "type": "us"
    },
    {
      "z1": 4785,
      "z2": 12839,
      "type": "us"
    },
    {
      "z1": 4809,
      "z2": 12819,
      "type": "us"
    },
    {
      "z1": 4826,
      "z2": 12811,
      "type": "us"
    },
    {
      "z1": 4840,
      "z2": 12800,
      "type": "us"
    },
    {
      "z1": 4857,
      "z2": 12743,
      "type": "us"
    },
    {
      "z1": 4894,
      "z2": 12674,
      "type": "us"
    },
    {
      "z1": 4926,
      "z2": 12649,
      "type": "us"
    },
    {
      "z1": 4951,
      "z2": 12633,
      "type": "us"
    },
    {
      "z1": 4992,
      "z2": 12487,
      "type": "us"
    },
    {
      "z1": 5026,
      "z2": 12431,
      "type": "us"
    },
    {
      "z1": 5039,
      "z2": 12375,
      "type": "us"
    },
    {
      "z1": 5081,
      "z2": 12351,
      "type": "us"
    },
    {
      "z1": 5128,
      "z2": 12344,
      "type": "us"
    },
    {
      "z1": 5132,
      "z2": 12313,
      "type": "us"
    },
    {
      "z1": 5147,
      "z2": 12233,
      "type": "us"
    },
    {
      "z1": 5187,
      "z2": 12178,
      "type": "us"
    },
    {
      "z1": 5234,
      "z2": 12066,
      "type": "us"
    },
    {
      "z1": 5274,
      "z2": 12044,
      "type": "us"
    },
    {
      "z1": 5294,
      "z2": 12002,
      "type": "us"
    },
    {
      "z1": 5324,
      "z2": 11986,
      "type": "us"
    },
    {
      "z1": 5336,
      "z2": 11978,
      "type": "us"
    },
    {
      "z1": 5341,
      "z2": 11956,
      "type": "us"
    },
    {
      "z1": 5358,
      "z2": 11948,
      "type": "us"
    },
    {
      "z1": 5365,
      "z2": 11895,
      "type": "us"
    },
    {
      "z1": 5410,
      "z2": 11838,
      "type": "us"
    },
    {
      "z1": 5420,
      "z2": 11816,
      "type": "us"
    },
    {
      "z1": 5447,
      "z2": 11800,
      "type": "us"
    },
    {
      "z1": 5458,
      "z2": 11766,
      "type": "us"
    },
    {
      "z1": 5473,
      "z2": 11742,
      "type": "us"
    },
    {
      "z1": 5490,
      "z2": 11734,
      "type": "us"
    },
    {
      "z1": 5503,
      "z2": 11726,
      "type": "us"
    },
    {
      "z1": 5511,
      "z2": 11717,
      "type": "us"
    },
    {
      "z1": 5535,
      "z2": 11704,
      "type": "us"
    },
    {
      "z1": 5536,
      "z2": 11701,
      "type": "us"
    },
    {
      "z1": 5545,
      "z2": 11682,
      "type": "us"
    },
    {
      "z1": 5568,
      "z2": 11649,
      "type": "us"
    },
    {
      "z1": 5573,
      "z2": 11624,
      "type": "us"
    },
    {
      "z1": 5586,
      "z2": 11621,
      "type": "us"
    },
    {
      "z1": 5589,
      "z2": 11578,
      "type": "us"
    },
    {
      "z1": 5606,
      "z2": 11570,
      "type": "us"
    },
    {
      "z1": 5615,
      "z2": 11507,
      "type": "us"
    },
    {
      "z1": 5646,
      "z2": 11401,
      "type": "us"
    },
    {
      "z1": 5693,
      "z2": 11289,
      "type": "se"
    },
    {
      "z1": 5758,
      "z2": 11240,
      "type": "us"
    },
    {
      "z1": 5780,
      "z2": 11239,
      "type": "us"
    },
    {
      "z1": 5822,
      "z2": 11215,
      "type": "us"
    },
    {
      "z1": 5824,
      "z2": 11179,
      "type": "us"
    },
    {
      "z1": 5840,
      "z2": 11124,
      "type": "us"
    },
    {
      "z1": 5857,
      "z2": 11116,
      "type": "us"
    },
    {
      "z1": 5887,
      "z2": 11012,
      "type": "us"
    },
    {
      "z1": 5904,
      "z2": 11004,
      "type": "us"
    },
    {
      "z1": 5954,
      "z2": 10971,
      "type": "us"
    },
    {
      "z1": 5987,
      "z2": 10894,
      "type": "us"
    },
    {
      "z1": 6017,
      "z2": 10876,
      "type": "us"
    },
    {
      "z1": 6037,
      "z2": 10834,
      "type": "us"
    },
    {
      "z1": 6062,
      "z2": 10818,
      "type": "us"
    },
    {
      "z1": 6074,
      "z2": 10730,
      "type": "us"
    },
    {
      "z1": 6133,
      "z2": 10724,
      "type": "us"
    },
    {
      "z1": 6139,
      "z2": 10681,
      "type": "us"
    },
    {
      "z1": 6153,
      "z2": 10670,
      "type": "us"
    },
    {
      "z1": 6178,
      "z2": 10654,
      "type": "us"
    },
    {
      "z1": 6180,
      "z2": 10612,
      "type": "us"
    },
    {
      "z1": 6219,
      "z2": 10526,
      "type": "us"
    },
    {
      "z1": 6236,
      "z2": 10518,
      "type": "us"
    },
    {
      "z1": 6266,
      "z2": 10414,
      "type": "us"
    },
    {
      "z1": 6283,
      "z2": 10406,
      "type": "us"
    },
    {
      "z1": 6314,
      "z2": 10400,
      "type": "us"
    },
    {
      "z1": 6345,
      "z2": 10396,
      "type": "us"
    },
    {
      "z1": 6355,
      "z2": 10383,
      "type": "us"
    },
    {
      "z1": 6366,
      "z2": 10296,
      "type": "us"
    },
    {
      "z1": 6389,
      "z2": 10233,
      "type": "us"
    },
    {
      "z1": 6413,
      "z2": 10194,
      "type": "us"
    },
    {
      "z1": 6436,
      "z2": 10121,
      "type": "se"
    },
    {
      "z1": 6514,
      "z2": 10073,
      "type": "us"
    },
    {
      "z1": 6561,
      "z2": 10053,
      "type": "us"
    },
    {
      "z1": 6567,
      "z2": 10011,
      "type": "us"
    },
    {
      "z1": 6608,
      "z2": 10005,
      "type": "us"
    },
    {
      "z1": 6610,
      "z2": 9970,
      "type": "us"
    },
    {
      "z1": 6632,
      "z2": 9942,
      "type": "us"
    },
    {
      "z1": 6647,
      "z2": 9855,
      "type": "us"
    },
    {
      "z1": 6664,
      "z2": 9847,
      "type": "us"
    },
    {
      "z1": 6695,
      "z2": 9841,
      "type": "us"
    },
    {
      "z1": 6726,
      "z2": 9837,
      "type": "us"
    },
    {
      "z1": 6737,
      "z2": 9781,
      "type": "us"
    },
    {
      "z1": 6747,
      "z2": 9737,
      "type": "us"
    },
    {
      "z1": 6794,
      "z2": 9635,
      "type": "us"
    },
    {
      "z1": 6817,
      "z2": 9562,
      "type": "us"
    },
    {
      "z1": 6876,
      "z2": 9556,
      "type": "us"
    },
    {
      "z1": 6886,
      "z2": 9513,
      "type": "us"
    },
    {
      "z1": 6893,
      "z2": 9475,
      "type": "us"
    },
    {
      "z1": 6923,
      "z2": 9444,
      "type": "us"
    },
    {
      "z1": 6960,
      "z2": 9390,
      "type": "us"
    },
    {
      "z1": 6977,
      "z2": 9382,
      "type": "us"
    },
    {
      "z1": 6995,
      "z2": 9356,
      "type": "us"
    },
    {
      "z1": 7007,
      "z2": 9278,
      "type": "us"
    },
    {
      "z1": 7024,
      "z2": 9270,
      "type": "us"
    },
    {
      "z1": 7057,
      "z2": 9232,
      "type": "us"
    },
    {
      "z1": 7088,
      "z2": 9228,
      "type": "us"
    },
    {
      "z1": 7107,
      "z2": 9160,
      "type": "us"
    },
    {
      "z1": 7109,
      "z2": 9138,
      "type": "us"
    },
    {
      "z1": 7154,
      "z2": 9128,
      "type": "us"
    },
    {
      "z1": 7156,
      "z2": 9026,
      "type": "se"
    },
    {
      "z1": 7270,
      "z2": 9021,
      "type": "us"
    },
    {
      "z1": 7271,
      "z2": 9006,
      "type": "us"
    },
    {
      "z1": 7274,
      "z2": 8916,
      "type": "us"
    },
    {
      "z1": 7304,
      "z2": 8885,
      "type": "us"
    },
    {
      "z1": 7329,
      "z2": 8845,
      "type": "us"
    },
    {
      "z1": 7376,
      "z2": 8797,
      "type": "us"
    },
    {
      "z1": 7388,
      "z2": 8719,
      "type": "us"
    },
    {
      "z1": 7405,
      "z2": 8711,
      "type": "us"
    },
    {
      "z1": 7438,
      "z2": 8673,
      "type": "us"
    },
    {
      "z1": 7469,
      "z2": 8669,
      "type": "us"
    },
    {
      "z1": 7488,
      "z2": 8601,
      "type": "us"
    },
    {
      "z1": 7535,
      "z2": 8569,
      "type": "us"
    },
    {
      "z1": 7537,
      "z2": 8467,
      "type": "se"
    },
    {
      "z1": 7587,
      "z2": 8451,
      "type": "us"
    },
    {
      "z1": 7629,
      "z2": 8345,
      "type": "us"
    },
    {
      "z1": 7634,
      "z2": 8339,
      "type": "us"
    },
    {
      "z1": 7691,
      "z2": 8300,
      "type": "us"
    },
    {
      "z1": 7738,
      "z2": 8188,
      "type": "us"
    },
    {
      "z1": 7827,
      "z2": 8142,
      "type": "us"
    },
    {
      "z1": 7847,
      "z2": 8139,
      "type": "us"
    },
    {
      "z1": 7877,
      "z2": 8098,
      "type": "us"
    },
    {
      "z1": 7884,
      "z2": 8079,
      "type": "us"
    },
    {
      "z1": 7889,
      "z2": 8065,
      "type": "us"
    },
    {
      "z1": 7900,
      "z2": 8043,
      "type": "us"
    },
    {
      "z1": 7926,
      "z2": 8042,
      "type": "us"
    },
    {
      "z1": 7939,
      "z2": 8008,
      "type": "us"
    },
    {
      "z1": 7968,
      "z2": 7998,
      "type": "us"
    },
    {
      "z1": 7995,
      "z2": 7975,
      "type": "us"
    },
    {
      "z1": 8012,
      "z2": 7870,
      "type": "us"
    },
    {
      "z1": 8015,
      "z2": 7780,
      "type": "us"
    },
    {
      "z1": 8084,
      "z2": 7772,
      "type": "us"
    },
    {
      "z1": 8119,
      "z2": 7629,
      "type": "se"
    },
    {
      "z1": 8177,
      "z2": 7598,
      "type": "us"
    },
    {
      "z1": 8200,
      "z2": 7543,
      "type": "us"
    },
    {
      "z1": 8239,
      "z2": 7508,
      "type": "us"
    },
    {
      "z1": 8244,
      "z2": 7502,
      "type": "us"
    },
    {
      "z1": 8307,
      "z2": 7483,
      "type": "us"
    },
    {
      "z1": 8327,
      "z2": 7429,
      "type": "us"
    },
    {
      "z1": 8328,
      "z2": 7421,
      "type": "us"
    },
    {
      "z1": 8361,
      "z2": 7383,
      "type": "us"
    },
    {
      "z1": 8374,
      "z2": 7317,
      "type": "us"
    },
    {
      "z1": 8437,
      "z2": 7305,
      "type": "us"
    },
    {
      "z1": 8458,
      "z2": 7284,
      "type": "us"
    },
    {
      "z1": 8463,
      "z2": 7271,
      "type": "us"
    },
    {
      "z1": 8487,
      "z2": 7261,
      "type": "us"
    },
    {
      "z1": 8491,
      "z2": 7245,
      "type": "us"
    },
    {
      "z1": 8499,
      "z2": 7228,
      "type": "us"
    },
    {
      "z1": 8515,
      "z2": 7197,
      "type": "us"
    },
    {
      "z1": 8520,
      "z2": 7191,
      "type": "us"
    },
    {
      "z1": 8571,
      "z2": 7180,
      "type": "us"
    },
    {
      "z1": 8576,
      "z2": 7174,
      "type": "us"
    },
    {
      "z1": 8578,
      "z2": 7173,
      "type": "us"
    },
    {
      "z1": 8585,
      "z2": 7072,
      "type": "us"
    },
    {
      "z1": 8625,
      "z2": 6943,
      "type": "us"
    },
    {
      "z1": 8693,
      "z2": 6929,
      "type": "us"
    },
    {
      "z1": 8701,
      "z2": 6889,
      "type": "us"
    },
    {
      "z1": 8709,
      "z2": 6862,
      "type": "us"
    },
    {
      "z1": 8742,
      "z2": 6824,
      "type": "us"
    },
    {
      "z1": 8755,
      "z2": 6758,
      "type": "se"
    },
    {
      "z1": 8824,
      "z2": 6750,
      "type": "us"
    },
    {
      "z1": 8839,
      "z2": 6725,
      "type": "us"
    },
    {
      "z1": 8867,
      "z2": 6688,
      "type": "us"
    },
    {
      "z1": 8871,
      "z2": 6680,
      "type": "us"
    },
    {
      "z1": 8875,
      "z2": 6678,
      "type": "us"
    },
    {
      "z1": 8885,
      "z2": 6632,
      "type": "us"
    },
    {
      "z1": 8917,
      "z2": 6576,
      "type": "us"
    },
    {
      "z1": 8981,
      "z2": 6556,
      "type": "us"
    },
    {
      "z1": 8997,
      "z2": 6512,
      "type": "us"
    },
    {
      "z1": 9034,
      "z2": 6469,
      "type": "us"
    },
    {
      "z1": 9063,
      "z2": 6450,
      "type": "us"
    },
    {
      "z1": 9073,
      "z2": 6434,
      "type": "us"
    },
    {
      "z1": 9083,
      "z2": 6429,
      "type": "us"
    },
    {
      "z1": 9097,
      "z2": 6396,
      "type": "us"
    },
    {
      "z1": 9138,
      "z2": 6380,
      "type": "us"
    },
    {
      "z1": 9143,
      "z2": 6374,
      "type": "us"
    },
    {
      "z1": 9148,
      "z2": 6356,
      "type": "us"
    },
    {
      "z1": 9160,
      "z2": 6278,
      "type": "us"
    },
    {
      "z1": 9208,
      "z2": 6267,
      "type": "us"
    },
    {
      "z1": 9235,
      "z2": 6204,
      "type": "us"
    },
    {
      "z1": 9241,
      "z2": 6182,
      "type": "us"
    },
    {
      "z1": 9277,
      "z2": 6159,
      "type": "us"
    },
    {
      "z1": 9311,
      "z2": 6052,
      "type": "us"
    },
    {
      "z1": 9317,
      "z2": 6038,
      "type": "us"
    },
    {
      "z1": 9378,
      "z2": 5953,
      "type": "us"
    },
    {
      "z1": 9397,
      "z2": 5896,
      "type": "se"
    },
    {
      "z1": 9478,
      "z2": 5893,
      "type": "us"
    },
    {
      "z1": 9479,
      "z2": 5856,
      "type": "us"
    },
    {
      "z1": 9491,
      "z2": 5844,
      "type": "us"
    },
    {
      "z1": 9496,
      "z2": 5833,
      "type": "us"
    },
    {
      "z1": 9511,
      "z2": 5807,
      "type": "us"
    },
    {
      "z1": 9540,
      "z2": 5771,
      "type": "us"
    },
    {
      "z1": 9577,
      "z2": 5727,
      "type": "us"
    },
    {
      "z1": 9616,
      "z2": 5688,
      "type": "us"
    },
    {
      "z1": 9638,
      "z2": 5652,
      "type": "us"
    },
    {
      "z1": 9686,
      "z2": 5633,
      "type": "us"
    },
    {
      "z1": 9694,
      "z2": 5630,
      "type": "us"
    },
    {
      "z1": 9696,
      "z2": 5625,
      "type": "us"
    },
    {
      "z1": 9715,
      "z2": 5620,
      "type": "us"
    },
    {
      "z1": 9719,
      "z2": 5558,
      "type": "us"
    },
    {
      "z1": 9745,
      "z2": 5543,
      "type": "us"
    },
    {
      "z1": 9765,
      "z2": 5473,
      "type": "us"
    },
    {
      "z1": 9819,
      "z2": 5469,
      "type": "us"
    },
    {
      "z1": 9828,
      "z2": 5430,
      "type": "us"
    },
    {
      "z1": 9846,
      "z2": 5405,
      "type": "us"
    },
    {
      "z1": 9853,
      "z2": 5401,
      "type": "us"
    },
    {
      "z1": 9870,
      "z2": 5391,
      "type": "us"
    },
    {
      "z1": 9873,
      "z2": 5348,
      "type": "us"
    },
    {
      "z1": 9879,
      "z2": 5318,
      "type": "us"
    },
    {
      "z1": 9907,
      "z2": 5265,
      "type": "us"
    },
    {
      "z1": 9941,
      "z2": 5225,
      "type": "us"
    },
    {
      "z1": 9959,
      "z2": 5192,
      "type": "us"
    },
    {
      "z1": 9975,
      "z2": 5182,
      "type": "us"
    },
    {
      "z1": 10003,
      "z2": 5147,
      "type": "us"
    },
    {
      "z1": 10020,
      "z2": 5091,
      "type": "us"
    },
    {
      "z1": 10073,
      "z2": 5087,
      "type": "us"
    },
    {
      "z1": 10077,
      "z2": 5066,
      "type": "us"
    },
    {
      "z1": 10096,
      "z2": 5008,
      "type": "us"
    },
    {
      "z1": 10101,
      "z2": 5007,
      "type": "us"
    },
    {
      "z1": 10134,
      "z2": 5002,
      "type": "us"
    },
    {
      "z1": 10145,
      "z2": 4978,
      "type": "us"
    },
    {
      "z1": 10177,
      "z2": 4949,
      "type": "us"
    },
    {
      "z1": 10185,
      "z2": 4926,
      "type": "us"
    },
    {
      "z1": 10190,
      "z2": 4915,
      "type": "us"
    },
    {
      "z1": 10200,
      "z2": 4910,
      "type": "us"
    },
    {
      "z1": 10239,
      "z2": 4883,
      "type": "us"
    },
    {
      "z1": 10260,
      "z2": 4855,
      "type": "us"
    },
    {
      "z1": 10261,
      "z2": 4847,
      "type": "us"
    },
    {
      "z1": 10276,
      "z2": 4839,
      "type": "us"
    },
    {
      "z1": 10290,
      "z2": 4818,
      "type": "us"
    },
    {
      "z1": 10308,
      "z2": 4785,
      "type": "us"
    },
    {
      "z1": 10324,
      "z2": 4769,
      "type": "us"
    },
    {
      "z1": 10330,
      "z2": 4759,
      "type": "us"
    },
    {
      "z1": 10332,
      "z2": 4754,
      "type": "us"
    },
    {
      "z1": 10340,
      "z2": 4729,
      "type": "us"
    },
    {
      "z1": 10357,
      "z2": 4631,
      "type": "us"
    },
    {
      "z1": 10401,
      "z2": 4602,
      "type": "us"
    },
    {
      "z1": 10441,
      "z2": 4550,
      "type": "us"
    },
    {
      "z1": 10480,
      "z2": 4526,
      "type": "us"
    },
    {
      "z1": 10530,
      "z2": 4522,
      "type": "us"
    },
    {
      "z1": 10540,
      "z2": 4506,
      "type": "us"
    },
    {
      "z1": 10554,
      "z2": 4500,
      "type": "us"
    },
    {
      "z1": 10560,
      "z2": 4490,
      "type": "us"
    },
    {
      "z1": 10562,
      "z2": 4460,
      "type": "us"
    },
    {
      "z1": 10564,
      "z2": 4420,
      "type": "us"
    },
    {
      "z1": 10571,
      "z2": 4397,
      "type": "us"
    },
    {
      "z1": 10582,
      "z2": 4387,
      "type": "us"
    },
    {
      "z1": 10583,
      "z2": 4380,
      "type": "us"
    },
    {
      "z1": 10606,
      "z2": 4371,
      "type": "us"
    },
    {
      "z1": 10615,
      "z2": 4368,
      "type": "us"
    },
    {
      "z1": 10626,
      "z2": 4330,
      "type": "us"
    },
    {
      "z1": 10663,
      "z2": 4303,
      "type": "us"
    },
    {
      "z1": 10666,
      "z2": 4279,
      "type": "us"
    },
    {
      "z1": 10700,
      "z2": 4261,
      "type": "us"
    },
    {
      "z1": 10702,
      "z2": 4259,
      "type": "us"
    },
    {
      "z1": 10703,
      "z2": 4247,
      "type": "us"
    },
    {
      "z1": 10713,
      "z2": 4195,
      "type": "us"
    },
    {
      "z1": 10740,
      "z2": 4175,
      "type": "us"
    },
    {
      "z1": 10774,
      "z2": 4145,
      "type": "us"
    },
    {
      "z1": 10799,
      "z2": 4111,
      "type": "us"
    },
    {
      "z1": 10802,
      "z2": 4082,
      "type": "us"
    },
    {
      "z1": 10820,
      "z2": 4049,
      "type": "us"
    },
    {
      "z1": 10836,
      "z2": 4039,
      "type": "us"
    },
    {
      "z1": 10877,
      "z2": 4036,
      "type": "us"
    },
    {
      "z1": 10881,
      "z2": 4018,
      "type": "us"
    },
    {
      "z1": 10914,
      "z2": 3997,
      "type": "us"
    },
    {
      "z1": 10919,
      "z2": 3986,
      "type": "us"
    },
    {
      "z1": 10921,
      "z2": 3966,
      "type": "us"
    },
    {
      "z1": 10934,
      "z2": 3960,
      "type": "us"
    },
    {
      "z1": 10955,
      "z2": 3949,
      "type": "us"
    },
    {
      "z1": 10963,
      "z2": 3924,
      "type": "us"
    },
    {
      "z1": 11013,
      "z2": 3921,
      "type": "us"
    },
    {
      "z1": 11025,
      "z2": 3909,
      "type": "us"
    },
    {
      "z1": 11028,
      "z2": 3880,
      "type": "us"
    },
    {
      "z1": 11044,
      "z2": 3836,
      "type": "us"
    },
    {
      "z1": 11066,
      "z2": 3799,
      "type": "us"
    },
    {
      "z1": 11086,
      "z2": 3777,
      "type": "us"
    },
    {
      "z1": 11103,
      "z2": 3721,
      "type": "us"
    },
    {
      "z1": 11142,
      "z2": 3711,
      "type": "us"
    },
    {
      "z1": 11148,
      "z2": 3710,
      "type": "us"
    },
    {
      "z1": 11168,
      "z2": 3667,
      "type": "us"
    },
    {
      "z1": 11181,
      "z2": 3560,
      "type": "us"
    },
    {
      "z1": 11218,
      "z2": 3488,
      "type": "se"
    },
    {
      "z1": 11262,
      "z2": 3459,
      "type": "us"
    },
    {
      "z1": 11302,
      "z2": 3407,
      "type": "us"
    },
    {
      "z1": 11336,
      "z2": 3390,
      "type": "us"
    },
    {
      "z1": 11374,
      "z2": 3382,
      "type": "us"
    },
    {
      "z1": 11389,
      "z2": 3372,
      "type": "us"
    },
    {
      "z1": 11401,
      "z2": 3363,
      "type": "us"
    },
    {
      "z1": 11407,
      "z2": 3358,
      "type": "us"
    },
    {
      "z1": 11410,
      "z2": 3312,
      "type": "us"
    },
    {
      "z1": 11425,
      "z2": 3277,
      "type": "us"
    },
    {
      "z1": 11443,
      "z2": 3244,
      "type": "us"
    },
    {
      "z1": 11447,
      "z2": 3240,
      "type": "us"
    },
    {
      "z1": 11500,
      "z2": 3231,
      "type": "us"
    },
    {
      "z1": 11514,
      "z2": 3219,
      "type": "us"
    },
    {
      "z1": 11524,
      "z2": 3160,
      "type": "us"
    },
    {
      "z1": 11557,
      "z2": 3155,
      "type": "us"
    },
    {
      "z1": 11568,
      "z2": 3131,
      "type": "us"
    },
    {
      "z1": 11608,
      "z2": 3079,
      "type": "us"
    },
    {
      "z1": 11647,
      "z2": 3075,
      "type": "us"
    },
    {
      "z1": 11665,
      "z2": 3066,
      "type": "us"
    },
    {
      "z1": 11673,
      "z2": 3038,
      "type": "us"
    },
    {
      "z1": 11724,
      "z2": 3035,
      "type": "us"
    },
    {
      "z1": 11731,
      "z2": 3033,
      "type": "us"
    },
    {
      "z1": 11733,
      "z2": 2985,
      "type": "us"
    },
    {
      "z1": 11743,
      "z2": 2971,
      "type": "us"
    },
    {
      "z1": 11753,
      "z2": 2912,
      "type": "us"
    },
    {
      "z1": 11820,
      "z2": 2906,
      "type": "us"
    },
    {
      "z1": 11831,
      "z2": 2843,
      "type": "us"
    },
    {
      "z1": 11851,
      "z2": 2770,
      "type": "us"
    },
    {
      "z1": 11895,
      "z2": 2741,
      "type": "us"
    },
    {
      "z1": 11926,
      "z2": 2737,
      "type": "us"
    },
    {
      "z1": 11943,
      "z2": 2721,
      "type": "us"
    },
    {
      "z1": 11946,
      "z2": 2699,
      "type": "us"
    },
    {
      "z1": 11956,
      "z2": 2687,
      "type": "us"
    },
    {
      "z1": 11972,
      "z2": 2639,
      "type": "us"
    },
    {
      "z1": 11988,
      "z2": 2586,
      "type": "us"
    },
    {
      "z1": 12009,
      "z2": 2567,
      "type": "us"
    },
    {
      "z1": 12029,
      "z2": 2524,
      "type": "us"
    },
    {
      "z1": 12073,
      "z2": 2495,
      "type": "us"
    },
    {
      "z1": 12079,
      "z2": 2491,
      "type": "us"
    },
    {
      "z1": 12089,
      "z2": 2432,
      "type": "us"
    },
    {
      "z1": 12133,
      "z2": 2403,
      "type": "us"
    },
    {
      "z1": 12188,
      "z2": 2369,
      "type": "us"
    },
    {
      "z1": 12217,
      "z2": 2366,
      "type": "us"
    },
    {
      "z1": 12232,
      "z2": 2335,
      "type": "us"
    },
    {
      "z1": 12234,
      "z2": 2314,
      "type": "us"
    },
    {
      "z1": 12258,
      "z2": 2276,
      "type": "us"
    },
    {
      "z1": 12319,
      "z2": 2275,
      "type": "us"
    },
    {
      "z1": 12325,
      "z2": 2264,
      "type": "us"
    },
    {
      "z1": 12350,
      "z2": 2254,
      "type": "us"
    },
    {
      "z1": 12351,
      "z2": 2245,
      "type": "us"
    },
    {
      "z1": 12363,
      "z2": 2221,
      "type": "us"
    },
    {
      "z1": 12392,
      "z2": 2210,
      "type": "us"
    },
    {
      "z1": 12394,
      "z2": 2209,
      "type": "us"
    },
    {
      "z1": 12403,
      "z2": 2198,
      "type": "us"
    },
    {
      "z1": 12413,
      "z2": 2139,
      "type": "us"
    },
    {
      "z1": 12461,
      "z2": 2129,
      "type": "us"
    },
    {
      "z1": 12464,
      "z2": 2108,
      "type": "us"
    },
    {
      "z1": 12505,
      "z2": 2100,
      "type": "us"
    },
    {
      "z1": 12512,
      "z2": 2081,
      "type": "us"
    },
    {
      "z1": 12528,
      "z2": 2019,
      "type": "us"
    },
    {
      "z1": 12560,
      "z2": 1989,
      "type": "us"
    },
    {
      "z1": 12580,
      "z2": 1916,
      "type": "us"
    },
    {
      "z1": 12598,
      "z2": 1902,
      "type": "us"
    },
    {
      "z1": 12641,
      "z2": 1888,
      "type": "us"
    },
    {
      "z1": 12642,
      "z2": 1873,
      "type": "us"
    },
    {
      "z1": 12678,
      "z2": 1816,
      "type": "us"
    },
    {
      "z1": 12690,
      "z2": 1777,
      "type": "us"
    },
    {
      "z1": 12692,
      "z2": 1700,
      "type": "us"
    },
    {
      "z1": 12702,
      "z2": 1686,
      "type": "us"
    },
    {
      "z1": 12712,
      "z2": 1627,
      "type": "se"
    },
    {
      "z1": 12756,
      "z2": 1598,
      "type": "us"
    },
    {
      "z1": 12828,
      "z2": 1567,
      "type": "us"
    },
    {
      "z1": 12843,
      "z2": 1536,
      "type": "us"
    },
    {
      "z1": 12870,
      "z2": 1523,
      "type": "us"
    },
    {
      "z1": 12899,
      "z2": 1498,
      "type": "us"
    },
    {
      "z1": 12923,
      "z2": 1478,
      "type": "us"
    },
    {
      "z1": 12972,
      "z2": 1473,
      "type": "us"
    },
    {
      "z1": 12978,
      "z2": 1449,
      "type": "us"
    },
    {
      "z1": 13011,
      "z2": 1446,
      "type": "us"
    },
    {
      "z1": 13014,
      "z2": 1399,
      "type": "us"
    },
    {
      "z1": 13024,
      "z2": 1340,
      "type": "se"
    },
    {
      "z1": 13117,
      "z2": 1306,
      "type": "us"
    },
    {
      "z1": 13123,
      "z2": 1282,
      "type": "us"
    },
    {
      "z1": 13192,
      "z2": 1250,
      "type": "us"
    },
    {
      "z1": 13278,
      "z2": 1246,
      "type": "us"
    },
    {
      "z1": 13285,
      "z2": 1216,
      "type": "us"
    },
    {
      "z1": 13291,
      "z2": 1192,
      "type": "us"
    },
    {
      "z1": 13297,
      "z2": 1174,
      "type": "se"
    },
    {
      "z1": 13390,
      "z2": 1140,
      "type": "us"
    },
    {
      "z1": 13412,
      "z2": 1136,
      "type": "us"
    },
    {
      "z1": 13465,
      "z2": 1084,
      "type": "se"
    },
    {
      "z1": 13540,
      "z2": 1054,
      "type": "us"
    },
    {
      "z1": 13558,
      "z2": 1050,
      "type": "us"
    },
    {
      "z1": 13569,
      "z2": 1046,
      "type": "us"
    },
    {
      "z1": 13640,
      "z2": 1040,
      "type": "us"
    },
    {
      "z1": 13649,
      "z2": 1037,
      "type": "us"
    },
    {
      "z1": 13662,
      "z2": 1012,
      "type": "us"
    },
    {
      "z1": 13733,
      "z2": 996,
      "type": "us"
    },
    {
      "z1": 13737,
      "z2": 956,
      "type": "us"
    },
    {
      "z1": 13777,
      "z2": 955,
      "type": "us"
    },
    {
      "z1": 13808,
      "z2": 951,
      "type": "us"
    },
    {
      "z1": 13830,
      "z2": 922,
      "type": "us"
    },
    {
      "z1": 13861,
      "z2": 914,
      "type": "us"
    },
    {
      "z1": 13889,
      "z2": 902,
      "type": "us"
    },
    {
      "z1": 13938,
      "z2": 895,
      "type": "us"
    },
    {
      "z1": 13955,
      "z2": 886,
      "type": "us"
    },
    {
      "z1": 13987,
      "z2": 880,
      "type": "us"
    },
    {
      "z1": 13998,
      "z2": 861,
      "type": "us"
    },
    {
      "z1": 14040,
      "z2": 820,
      "type": "us"
    },
    {
      "z1": 14096,
      "z2": 785,
      "type": "se"
    },
    {
      "z1": 14187,
      "z2": 757,
      "type": "se"
    },
    {
      "z1": 14316,
      "z2": 734,
      "type": "us"
    },
    {
      "z1": 14369,
      "z2": 725,
      "type": "us"
    },
    {
      "z1": 14401,
      "z2": 719,
      "type": "us"
    },
    {
      "z1": 14428,
      "z2": 716,
      "type": "us"
    },
    {
      "z1": 14483,
      "z2": 709,
      "type": "us"
    },
    {
      "z1": 14546,
      "z2": 701,
      "type": "us"
    },
    {
      "z1": 14603,
      "z2": 691,
      "type": "us"
    },
    {
      "z1": 14612,
      "z2": 686,
      "type": "us"
    },
    {
      "z1": 14621,
      "z2": 668,
      "type": "us"
    },
    {
      "z1": 14623,
      "z2": 664,
      "type": "us"
    },
    {
      "z1": 14721,
      "z2": 646,
      "type": "us"
    },
    {
      "z1": 14761,
      "z2": 644,
      "type": "us"
    },
    {
      "z1": 14832,
      "z2": 639,
      "type": "us"
    },
    {
      "z1": 14843,
      "z2": 613,
      "type": "se"
    },
    {
      "z1": 14941,
      "z2": 595,
      "type": "sne"
    },
    {
      "z1": 14981,
      "z2": 593,
      "type": "us"
    },
    {
      "z1": 15039,
      "z2": 577,
      "type": "se"
    },
    {
      "z1": 15162,
      "z2": 570,
      "type": "us"
    },
    {
      "z1": 15199,
      "z2": 568,
      "type": "us"
    },
    {
      "z1": 15254,
      "z2": 567,
      "type": "us"
    },
    {
      "z1": 15273,
      "z2": 563,
      "type": "us"
    },
    {
      "z1": 15288,
      "z2": 562,
      "type": "us"
    },
    {
      "z1": 15298,
      "z2": 542,
      "type": "us"
    },
    {
      "z1": 15428,
      "z2": 538,
      "type": "us"
    },
    {
      "z1": 15499,
      "z2": 527,
      "type": "us"
    },
    {
      "z1": 15507,
      "z2": 512,
      "type": "us"
    },
    {
      "z1": 15540,
      "z2": 505,
      "type": "se"
    },
    {
      "z1": 15670,
      "z2": 501,
      "type": "us"
    },
    {
      "z1": 15673,
      "z2": 499,
      "type": "us"
    },
    {
      "z1": 15695,
      "z2": 491,
      "type": "se"
    },
    {
      "z1": 15818,
      "z2": 484,
      "type": "us"
    },
    {
      "z1": 15858,
      "z2": 482,
      "type": "us"
    },
    {
      "z1": 15894,
      "z2": 474,
      "type": "se"
    },
    {
      "z1": 16024,
      "z2": 470,
      "type": "us"
    },
    {
      "z1": 16134,
      "z2": 469,
      "type": "us"
    },
    {
      "z1": 16167,
      "z2": 462,
      "type": "us"
    },
    {
      "z1": 16207,
      "z2": 460,
      "type": "us"
    },
    {
      "z1": 16338,
      "z2": 456,
      "type": "us"
    },
    {
      "z1": 16396,
      "z2": 449,
      "type": "us"
    },
    {
      "z1": 16398,
      "z2": 438,
      "type": "us"
    },
    {
      "z1": 16537,
      "z2": 437,
      "type": "us"
    },
    {
      "z1": 16562,
      "z2": 436,
      "type": "us"
    },
    {
      "z1": 16605,
      "z2": 427,
      "type": "us"
    },
    {
      "z1": 16638,
      "z2": 420,
      "type": "us"
    },
    {
      "z1": 16771,
      "z2": 414,
      "type": "us"
    },
    {
      "z1": 16783,
      "z2": 411,
      "type": "us"
    },
    {
      "z1": 16939,
      "z2": 406,
      "type": "us"
    },
    {
      "z1": 16992,
      "z2": 389,
      "type": "se"
    }
  ]
}
